<?xml version="1.0" encoding="utf-8"?>
<Exports>
  <Tag>
    <SortPriority>0</SortPriority>
    <IsChecked>false</IsChecked>
    <IsExpanded>false</IsExpanded>
    <Enabled>true</Enabled>
    <ID>393621bf-854b-45d0-bf0a-967273c9628c</ID>
    <Name>02_ult_VS_Bahamut-Nael</Name>
  </Tag>
  <Panels>
    <PanelSettings>
      <SortPriority>0</SortPriority>
      <IsChecked>false</IsChecked>
      <IsExpanded>false</IsExpanded>
      <Enabled>true</Enabled>
      <PanelName>02_ult_VS_Bahamut-Nael Words</PanelName>
      <ID>f27167af-218a-483a-981f-ff479a9d612d</ID>
      <Left>1180</Left>
      <Locked>false</Locked>
      <Top>640</Top>
      <Margin>0</Margin>
      <Horizontal>false</Horizontal>
      <SortOrder>SortRecastTimeASC</SortOrder>
      <EnabledAdvancedLayout>false</EnabledAdvancedLayout>
      <Width>640</Width>
      <Height>480</Height>
      <GridPadding>0 0 0 0</GridPadding>
      <GridVerticalAlignment>Stretch</GridVerticalAlignment>
      <GridHorizontalAlignment>Stretch</GridHorizontalAlignment>
      <IsStackLayout>false</IsStackLayout>
      <StackPanelOrientation>Vertical</StackPanelOrientation>
      <FixedPositionSpell>false</FixedPositionSpell>
      <BackgroundColor>
        <A>160</A>
        <R>0</R>
        <G>0</G>
        <B>0</B>
        <ScA>0.627451</ScA>
        <ScR>0</ScR>
        <ScG>0</ScG>
        <ScB>0</ScB>
      </BackgroundColor>
    </PanelSettings>
    <PanelSettings>
      <SortPriority>0</SortPriority>
      <IsChecked>false</IsChecked>
      <IsExpanded>false</IsExpanded>
      <Enabled>true</Enabled>
      <PanelName>02_ult_VS_Bahamut-Neal Chain Lightning</PanelName>
      <ID>9f50e2b1-8283-4e6e-96c2-d584b0c8765a</ID>
      <Left>1850</Left>
      <Locked>false</Locked>
      <Top>640</Top>
      <Margin>30</Margin>
      <Horizontal>true</Horizontal>
      <SortOrder>SortPriority</SortOrder>
      <EnabledAdvancedLayout>false</EnabledAdvancedLayout>
      <Width>640</Width>
      <Height>480</Height>
      <GridPadding>0 0 0 0</GridPadding>
      <GridVerticalAlignment>Stretch</GridVerticalAlignment>
      <GridHorizontalAlignment>Stretch</GridHorizontalAlignment>
      <IsStackLayout>false</IsStackLayout>
      <StackPanelOrientation>Vertical</StackPanelOrientation>
      <FixedPositionSpell>false</FixedPositionSpell>
      <BackgroundColor>
        <A>160</A>
        <R>0</R>
        <G>0</G>
        <B>0</B>
        <ScA>0.627451</ScA>
        <ScR>0</ScR>
        <ScG>0</ScG>
        <ScB>0</ScB>
      </BackgroundColor>
    </PanelSettings>
  </Panels>
  <Spells>
    <SpellTimer>
      <SortPriority>0</SortPriority>
      <IsChecked>false</IsChecked>
      <IsExpanded>false</IsExpanded>
      <Enabled>true</Enabled>
      <IsCircleStyle>false</IsCircleStyle>
      <TitleVerticalAlignmentInCircle>Center</TitleVerticalAlignmentInCircle>
      <Left>0</Left>
      <Top>0</Top>
      <ID>10</ID>
      <Guid>6bb4a70b-36d3-45ff-89ee-c9ad72cdfd46</Guid>
      <PanelID>f27167af-218a-483a-981f-ff479a9d612d</PanelID>
      <Panel>02_ult_VS_Bahamut-Nael Words</Panel>
      <SpellTitle>　内周安置,⇒頭割</SpellTitle>
      <RegexEnabled>false</RegexEnabled>
      <Keyword>月よ！ 赤熱し、神敵を焼け！</Keyword>
      <RecastTime>10</RecastTime>
      <DelayToShow>0</DelayToShow>
      <RecastTimeExtending1>0</RecastTimeExtending1>
      <RecastTimeExtending2>0</RecastTimeExtending2>
      <RecastTimeExtending3>0</RecastTimeExtending3>
      <OverlapRecastTime>false</OverlapRecastTime>
      <IsNotResetBarOnExtended>false</IsNotResetBarOnExtended>
      <ProgressBarVisible>true</ProgressBarVisible>
      <Font FontFamily="Yu Gothic UI" Size="30" Stretch="Normal" Style="Normal" Weight="Bold" />
      <FontColor>#DC143C</FontColor>
      <FontOutlineColor>#FFFFFF</FontOutlineColor>
      <WarningTime>0</WarningTime>
      <ChangeFontColorsWhenWarning>false</ChangeFontColorsWhenWarning>
      <WarningFontColor>#FFFFFF</WarningFontColor>
      <WarningFontOutlineColor>#FF4500</WarningFontOutlineColor>
      <ChangeFontColorWhenContainsMe>false</ChangeFontColorWhenContainsMe>
      <BarWidth>285</BarWidth>
      <BarHeight>0</BarHeight>
      <BarColor>#FFFFFF</BarColor>
      <BarOutlineColor>#191970</BarOutlineColor>
      <BarBlurRadius>11</BarBlurRadius>
      <BackgroundColor>#FFFFFF</BackgroundColor>
      <BackgroundAlpha>0</BackgroundAlpha>
      <DisplayNo>100</DisplayNo>
      <DontHide>false</DontHide>
      <IsHideInNotCombat>false</IsHideInNotCombat>
      <ExtendBeyondOriginalRecastTime>false</ExtendBeyondOriginalRecastTime>
      <HideSpellName>false</HideSpellName>
      <HideCounter>true</HideCounter>
      <IsCounterToCenter>false</IsCounterToCenter>
      <IsReverse>false</IsReverse>
      <MatchDateTime>0001-01-01T00:00:00</MatchDateTime>
      <UseHotbarRecastTime>false</UseHotbarRecastTime>
      <HotbarName />
      <ReduceIconBrightness>false</ReduceIconBrightness>
      <SpellIcon />
      <SpellIconSize>24</SpellIconSize>
      <IsNotResetAtWipeout>false</IsNotResetAtWipeout>
      <TimeupHide>false</TimeupHide>
      <ToInstance>false</ToInstance>
      <UpperLimitOfExtension>0</UpperLimitOfExtension>
      <BlinkTime>0</BlinkTime>
      <BlinkIcon>false</BlinkIcon>
      <BlinkBar>false</BlinkBar>
      <JobFilter />
      <PartyJobFilter />
      <PartyCompositionFilter />
      <ZoneFilter />
      <TimersMustRunningForStart />
      <TimersMustStoppingForStart />
      <ExpressionFilter>
        <expression />
        <expression />
        <expression />
        <expression />
      </ExpressionFilter>
      <IsSequentialTTS>false</IsSequentialTTS>
      <MatchTextToSpeak />
      <MatchAdvancedConfig>
        <IsEnabled>false</IsEnabled>
        <ToMainDevice>true</ToMainDevice>
        <ToSubDevice>false</ToSubDevice>
        <ToDicordTextChat>false</ToDicordTextChat>
        <Palette>Default</Palette>
      </MatchAdvancedConfig>
      <OverTime>0</OverTime>
      <OverTextToSpeak />
      <OverAdvancedConfig>
        <IsEnabled>false</IsEnabled>
        <ToMainDevice>true</ToMainDevice>
        <ToSubDevice>false</ToSubDevice>
        <ToDicordTextChat>false</ToDicordTextChat>
        <Palette>Default</Palette>
      </OverAdvancedConfig>
      <BeforeTime>0</BeforeTime>
      <BeforeTextToSpeak />
      <BeforeAdvancedConfig>
        <IsEnabled>false</IsEnabled>
        <ToMainDevice>true</ToMainDevice>
        <ToSubDevice>false</ToSubDevice>
        <ToDicordTextChat>false</ToDicordTextChat>
        <Palette>Default</Palette>
      </BeforeAdvancedConfig>
      <TimeupTextToSpeak />
      <TimeupAdvancedConfig>
        <IsEnabled>false</IsEnabled>
        <ToMainDevice>true</ToMainDevice>
        <ToSubDevice>false</ToSubDevice>
        <ToDicordTextChat>false</ToDicordTextChat>
        <Palette>Default</Palette>
      </TimeupAdvancedConfig>
      <MatchSound />
      <OverSound />
      <BeforeSound />
      <TimeupSound />
    </SpellTimer>
    <SpellTimer>
      <SortPriority>0</SortPriority>
      <IsChecked>false</IsChecked>
      <IsExpanded>false</IsExpanded>
      <Enabled>true</Enabled>
      <IsCircleStyle>false</IsCircleStyle>
      <TitleVerticalAlignmentInCircle>Center</TitleVerticalAlignmentInCircle>
      <Left>0</Left>
      <Top>0</Top>
      <ID>11</ID>
      <Guid>c3ab75d6-01d7-4ad4-afdf-118fb064bc61</Guid>
      <PanelID>f27167af-218a-483a-981f-ff479a9d612d</PanelID>
      <Panel>02_ult_VS_Bahamut-Nael Words</Panel>
      <SpellTitle>　内周安置,⇒外周安置</SpellTitle>
      <RegexEnabled>false</RegexEnabled>
      <Keyword>月よ！ 鉄の覇道を照らせ！</Keyword>
      <RecastTime>10</RecastTime>
      <DelayToShow>0</DelayToShow>
      <RecastTimeExtending1>0</RecastTimeExtending1>
      <RecastTimeExtending2>0</RecastTimeExtending2>
      <RecastTimeExtending3>0</RecastTimeExtending3>
      <OverlapRecastTime>false</OverlapRecastTime>
      <IsNotResetBarOnExtended>false</IsNotResetBarOnExtended>
      <ProgressBarVisible>true</ProgressBarVisible>
      <Font FontFamily="Yu Gothic UI" Size="30" Stretch="Normal" Style="Normal" Weight="Bold" />
      <FontColor>#DC143C</FontColor>
      <FontOutlineColor>#FFFFFF</FontOutlineColor>
      <WarningTime>0</WarningTime>
      <ChangeFontColorsWhenWarning>false</ChangeFontColorsWhenWarning>
      <WarningFontColor>#FFFFFF</WarningFontColor>
      <WarningFontOutlineColor>#FF4500</WarningFontOutlineColor>
      <ChangeFontColorWhenContainsMe>false</ChangeFontColorWhenContainsMe>
      <BarWidth>285</BarWidth>
      <BarHeight>0</BarHeight>
      <BarColor>#FFFFFF</BarColor>
      <BarOutlineColor>#191970</BarOutlineColor>
      <BarBlurRadius>11</BarBlurRadius>
      <BackgroundColor>#FFFFFF</BackgroundColor>
      <BackgroundAlpha>0</BackgroundAlpha>
      <DisplayNo>101</DisplayNo>
      <DontHide>false</DontHide>
      <IsHideInNotCombat>false</IsHideInNotCombat>
      <ExtendBeyondOriginalRecastTime>false</ExtendBeyondOriginalRecastTime>
      <HideSpellName>false</HideSpellName>
      <HideCounter>true</HideCounter>
      <IsCounterToCenter>false</IsCounterToCenter>
      <IsReverse>false</IsReverse>
      <MatchDateTime>0001-01-01T00:00:00</MatchDateTime>
      <UseHotbarRecastTime>false</UseHotbarRecastTime>
      <HotbarName />
      <ReduceIconBrightness>false</ReduceIconBrightness>
      <SpellIcon />
      <SpellIconSize>24</SpellIconSize>
      <IsNotResetAtWipeout>false</IsNotResetAtWipeout>
      <TimeupHide>false</TimeupHide>
      <ToInstance>false</ToInstance>
      <UpperLimitOfExtension>0</UpperLimitOfExtension>
      <BlinkTime>0</BlinkTime>
      <BlinkIcon>false</BlinkIcon>
      <BlinkBar>false</BlinkBar>
      <JobFilter />
      <PartyJobFilter />
      <PartyCompositionFilter />
      <ZoneFilter />
      <TimersMustRunningForStart />
      <TimersMustStoppingForStart />
      <ExpressionFilter>
        <expression />
        <expression />
        <expression />
        <expression />
      </ExpressionFilter>
      <IsSequentialTTS>false</IsSequentialTTS>
      <MatchTextToSpeak />
      <MatchAdvancedConfig>
        <IsEnabled>false</IsEnabled>
        <ToMainDevice>true</ToMainDevice>
        <ToSubDevice>false</ToSubDevice>
        <ToDicordTextChat>false</ToDicordTextChat>
        <Palette>Default</Palette>
      </MatchAdvancedConfig>
      <OverTime>0</OverTime>
      <OverTextToSpeak />
      <OverAdvancedConfig>
        <IsEnabled>false</IsEnabled>
        <ToMainDevice>true</ToMainDevice>
        <ToSubDevice>false</ToSubDevice>
        <ToDicordTextChat>false</ToDicordTextChat>
        <Palette>Default</Palette>
      </OverAdvancedConfig>
      <BeforeTime>0</BeforeTime>
      <BeforeTextToSpeak />
      <BeforeAdvancedConfig>
        <IsEnabled>false</IsEnabled>
        <ToMainDevice>true</ToMainDevice>
        <ToSubDevice>false</ToSubDevice>
        <ToDicordTextChat>false</ToDicordTextChat>
        <Palette>Default</Palette>
      </BeforeAdvancedConfig>
      <TimeupTextToSpeak />
      <TimeupAdvancedConfig>
        <IsEnabled>false</IsEnabled>
        <ToMainDevice>true</ToMainDevice>
        <ToSubDevice>false</ToSubDevice>
        <ToDicordTextChat>false</ToDicordTextChat>
        <Palette>Default</Palette>
      </TimeupAdvancedConfig>
      <MatchSound />
      <OverSound />
      <BeforeSound />
      <TimeupSound />
    </SpellTimer>
    <SpellTimer>
      <SortPriority>0</SortPriority>
      <IsChecked>false</IsChecked>
      <IsExpanded>false</IsExpanded>
      <Enabled>true</Enabled>
      <IsCircleStyle>false</IsCircleStyle>
      <TitleVerticalAlignmentInCircle>Center</TitleVerticalAlignmentInCircle>
      <Left>0</Left>
      <Top>0</Top>
      <ID>12</ID>
      <Guid>e18f036e-46fb-4da0-bf47-98f13dbd0f9c</Guid>
      <PanelID>f27167af-218a-483a-981f-ff479a9d612d</PanelID>
      <Panel>02_ult_VS_Bahamut-Nael Words</Panel>
      <SpellTitle>　頭割,⇒外周安置</SpellTitle>
      <RegexEnabled>false</RegexEnabled>
      <Keyword>赤熱し、焼かれし道を 鉄の覇道と成す！</Keyword>
      <RecastTime>10</RecastTime>
      <DelayToShow>0</DelayToShow>
      <RecastTimeExtending1>0</RecastTimeExtending1>
      <RecastTimeExtending2>0</RecastTimeExtending2>
      <RecastTimeExtending3>0</RecastTimeExtending3>
      <OverlapRecastTime>false</OverlapRecastTime>
      <IsNotResetBarOnExtended>false</IsNotResetBarOnExtended>
      <ProgressBarVisible>true</ProgressBarVisible>
      <Font FontFamily="Yu Gothic UI" Size="30" Stretch="Normal" Style="Normal" Weight="Bold" />
      <FontColor>#DC143C</FontColor>
      <FontOutlineColor>#FFFFFF</FontOutlineColor>
      <WarningTime>0</WarningTime>
      <ChangeFontColorsWhenWarning>false</ChangeFontColorsWhenWarning>
      <WarningFontColor>#FFFFFF</WarningFontColor>
      <WarningFontOutlineColor>#FF4500</WarningFontOutlineColor>
      <ChangeFontColorWhenContainsMe>false</ChangeFontColorWhenContainsMe>
      <BarWidth>285</BarWidth>
      <BarHeight>0</BarHeight>
      <BarColor>#FFFFFF</BarColor>
      <BarOutlineColor>#191970</BarOutlineColor>
      <BarBlurRadius>11</BarBlurRadius>
      <BackgroundColor>#FFFFFF</BackgroundColor>
      <BackgroundAlpha>0</BackgroundAlpha>
      <DisplayNo>102</DisplayNo>
      <DontHide>false</DontHide>
      <IsHideInNotCombat>false</IsHideInNotCombat>
      <ExtendBeyondOriginalRecastTime>false</ExtendBeyondOriginalRecastTime>
      <HideSpellName>false</HideSpellName>
      <HideCounter>true</HideCounter>
      <IsCounterToCenter>false</IsCounterToCenter>
      <IsReverse>false</IsReverse>
      <MatchDateTime>0001-01-01T00:00:00</MatchDateTime>
      <UseHotbarRecastTime>false</UseHotbarRecastTime>
      <HotbarName />
      <ReduceIconBrightness>false</ReduceIconBrightness>
      <SpellIcon />
      <SpellIconSize>24</SpellIconSize>
      <IsNotResetAtWipeout>false</IsNotResetAtWipeout>
      <TimeupHide>false</TimeupHide>
      <ToInstance>false</ToInstance>
      <UpperLimitOfExtension>0</UpperLimitOfExtension>
      <BlinkTime>0</BlinkTime>
      <BlinkIcon>false</BlinkIcon>
      <BlinkBar>false</BlinkBar>
      <JobFilter />
      <PartyJobFilter />
      <PartyCompositionFilter />
      <ZoneFilter />
      <TimersMustRunningForStart />
      <TimersMustStoppingForStart />
      <ExpressionFilter>
        <expression />
        <expression />
        <expression />
        <expression />
      </ExpressionFilter>
      <IsSequentialTTS>false</IsSequentialTTS>
      <MatchTextToSpeak />
      <MatchAdvancedConfig>
        <IsEnabled>false</IsEnabled>
        <ToMainDevice>true</ToMainDevice>
        <ToSubDevice>false</ToSubDevice>
        <ToDicordTextChat>false</ToDicordTextChat>
        <Palette>Default</Palette>
      </MatchAdvancedConfig>
      <OverTime>0</OverTime>
      <OverTextToSpeak />
      <OverAdvancedConfig>
        <IsEnabled>false</IsEnabled>
        <ToMainDevice>true</ToMainDevice>
        <ToSubDevice>false</ToSubDevice>
        <ToDicordTextChat>false</ToDicordTextChat>
        <Palette>Default</Palette>
      </OverAdvancedConfig>
      <BeforeTime>0</BeforeTime>
      <BeforeTextToSpeak />
      <BeforeAdvancedConfig>
        <IsEnabled>false</IsEnabled>
        <ToMainDevice>true</ToMainDevice>
        <ToSubDevice>false</ToSubDevice>
        <ToDicordTextChat>false</ToDicordTextChat>
        <Palette>Default</Palette>
      </BeforeAdvancedConfig>
      <TimeupTextToSpeak />
      <TimeupAdvancedConfig>
        <IsEnabled>false</IsEnabled>
        <ToMainDevice>true</ToMainDevice>
        <ToSubDevice>false</ToSubDevice>
        <ToDicordTextChat>false</ToDicordTextChat>
        <Palette>Default</Palette>
      </TimeupAdvancedConfig>
      <MatchSound />
      <OverSound />
      <BeforeSound />
      <TimeupSound />
    </SpellTimer>
    <SpellTimer>
      <SortPriority>0</SortPriority>
      <IsChecked>false</IsChecked>
      <IsExpanded>false</IsExpanded>
      <Enabled>true</Enabled>
      <IsCircleStyle>false</IsCircleStyle>
      <TitleVerticalAlignmentInCircle>Center</TitleVerticalAlignmentInCircle>
      <Left>0</Left>
      <Top>0</Top>
      <ID>13</ID>
      <Guid>290ed5ae-7191-472f-8ba7-8229b739f4af</Guid>
      <PanelID>f27167af-218a-483a-981f-ff479a9d612d</PanelID>
      <Panel>02_ult_VS_Bahamut-Nael Words</Panel>
      <SpellTitle>　頭割,⇒内周安置</SpellTitle>
      <RegexEnabled>false</RegexEnabled>
      <Keyword>赤熱せし 月の祝福を！</Keyword>
      <RecastTime>10</RecastTime>
      <DelayToShow>0</DelayToShow>
      <RecastTimeExtending1>0</RecastTimeExtending1>
      <RecastTimeExtending2>0</RecastTimeExtending2>
      <RecastTimeExtending3>0</RecastTimeExtending3>
      <OverlapRecastTime>false</OverlapRecastTime>
      <IsNotResetBarOnExtended>false</IsNotResetBarOnExtended>
      <ProgressBarVisible>true</ProgressBarVisible>
      <Font FontFamily="Yu Gothic UI" Size="30" Stretch="Normal" Style="Normal" Weight="Bold" />
      <FontColor>#DC143C</FontColor>
      <FontOutlineColor>#FFFFFF</FontOutlineColor>
      <WarningTime>0</WarningTime>
      <ChangeFontColorsWhenWarning>false</ChangeFontColorsWhenWarning>
      <WarningFontColor>#FFFFFF</WarningFontColor>
      <WarningFontOutlineColor>#FF4500</WarningFontOutlineColor>
      <ChangeFontColorWhenContainsMe>false</ChangeFontColorWhenContainsMe>
      <BarWidth>285</BarWidth>
      <BarHeight>0</BarHeight>
      <BarColor>#FFFFFF</BarColor>
      <BarOutlineColor>#191970</BarOutlineColor>
      <BarBlurRadius>11</BarBlurRadius>
      <BackgroundColor>#FFFFFF</BackgroundColor>
      <BackgroundAlpha>0</BackgroundAlpha>
      <DisplayNo>103</DisplayNo>
      <DontHide>false</DontHide>
      <IsHideInNotCombat>false</IsHideInNotCombat>
      <ExtendBeyondOriginalRecastTime>false</ExtendBeyondOriginalRecastTime>
      <HideSpellName>false</HideSpellName>
      <HideCounter>true</HideCounter>
      <IsCounterToCenter>false</IsCounterToCenter>
      <IsReverse>false</IsReverse>
      <MatchDateTime>0001-01-01T00:00:00</MatchDateTime>
      <UseHotbarRecastTime>false</UseHotbarRecastTime>
      <HotbarName />
      <ReduceIconBrightness>false</ReduceIconBrightness>
      <SpellIcon />
      <SpellIconSize>24</SpellIconSize>
      <IsNotResetAtWipeout>false</IsNotResetAtWipeout>
      <TimeupHide>false</TimeupHide>
      <ToInstance>false</ToInstance>
      <UpperLimitOfExtension>0</UpperLimitOfExtension>
      <BlinkTime>0</BlinkTime>
      <BlinkIcon>false</BlinkIcon>
      <BlinkBar>false</BlinkBar>
      <JobFilter />
      <PartyJobFilter />
      <PartyCompositionFilter />
      <ZoneFilter />
      <TimersMustRunningForStart />
      <TimersMustStoppingForStart />
      <ExpressionFilter>
        <expression />
        <expression />
        <expression />
        <expression />
      </ExpressionFilter>
      <IsSequentialTTS>false</IsSequentialTTS>
      <MatchTextToSpeak />
      <MatchAdvancedConfig>
        <IsEnabled>false</IsEnabled>
        <ToMainDevice>true</ToMainDevice>
        <ToSubDevice>false</ToSubDevice>
        <ToDicordTextChat>false</ToDicordTextChat>
        <Palette>Default</Palette>
      </MatchAdvancedConfig>
      <OverTime>0</OverTime>
      <OverTextToSpeak />
      <OverAdvancedConfig>
        <IsEnabled>false</IsEnabled>
        <ToMainDevice>true</ToMainDevice>
        <ToSubDevice>false</ToSubDevice>
        <ToDicordTextChat>false</ToDicordTextChat>
        <Palette>Default</Palette>
      </OverAdvancedConfig>
      <BeforeTime>0</BeforeTime>
      <BeforeTextToSpeak />
      <BeforeAdvancedConfig>
        <IsEnabled>false</IsEnabled>
        <ToMainDevice>true</ToMainDevice>
        <ToSubDevice>false</ToSubDevice>
        <ToDicordTextChat>false</ToDicordTextChat>
        <Palette>Default</Palette>
      </BeforeAdvancedConfig>
      <TimeupTextToSpeak />
      <TimeupAdvancedConfig>
        <IsEnabled>false</IsEnabled>
        <ToMainDevice>true</ToMainDevice>
        <ToSubDevice>false</ToSubDevice>
        <ToDicordTextChat>false</ToDicordTextChat>
        <Palette>Default</Palette>
      </TimeupAdvancedConfig>
      <MatchSound />
      <OverSound />
      <BeforeSound />
      <TimeupSound />
    </SpellTimer>
    <SpellTimer>
      <SortPriority>0</SortPriority>
      <IsChecked>false</IsChecked>
      <IsExpanded>false</IsExpanded>
      <Enabled>true</Enabled>
      <IsCircleStyle>false</IsCircleStyle>
      <TitleVerticalAlignmentInCircle>Center</TitleVerticalAlignmentInCircle>
      <Left>0</Left>
      <Top>0</Top>
      <ID>14</ID>
      <Guid>25f013d2-d999-490a-adb4-70957f864fe8</Guid>
      <PanelID>f27167af-218a-483a-981f-ff479a9d612d</PanelID>
      <Panel>02_ult_VS_Bahamut-Nael Words</Panel>
      <SpellTitle>　ランダム1名にAoE,⇒内周安置</SpellTitle>
      <RegexEnabled>false</RegexEnabled>
      <Keyword>我、舞い降りて 月を仰がん！</Keyword>
      <RecastTime>10</RecastTime>
      <DelayToShow>0</DelayToShow>
      <RecastTimeExtending1>0</RecastTimeExtending1>
      <RecastTimeExtending2>0</RecastTimeExtending2>
      <RecastTimeExtending3>0</RecastTimeExtending3>
      <OverlapRecastTime>false</OverlapRecastTime>
      <IsNotResetBarOnExtended>false</IsNotResetBarOnExtended>
      <ProgressBarVisible>true</ProgressBarVisible>
      <Font FontFamily="Yu Gothic UI" Size="30" Stretch="Normal" Style="Normal" Weight="Bold" />
      <FontColor>#DC143C</FontColor>
      <FontOutlineColor>#FFFFFF</FontOutlineColor>
      <WarningTime>0</WarningTime>
      <ChangeFontColorsWhenWarning>false</ChangeFontColorsWhenWarning>
      <WarningFontColor>#FFFFFF</WarningFontColor>
      <WarningFontOutlineColor>#FF4500</WarningFontOutlineColor>
      <ChangeFontColorWhenContainsMe>false</ChangeFontColorWhenContainsMe>
      <BarWidth>285</BarWidth>
      <BarHeight>0</BarHeight>
      <BarColor>#FFFFFF</BarColor>
      <BarOutlineColor>#191970</BarOutlineColor>
      <BarBlurRadius>11</BarBlurRadius>
      <BackgroundColor>#FFFFFF</BackgroundColor>
      <BackgroundAlpha>0</BackgroundAlpha>
      <DisplayNo>104</DisplayNo>
      <DontHide>false</DontHide>
      <IsHideInNotCombat>false</IsHideInNotCombat>
      <ExtendBeyondOriginalRecastTime>false</ExtendBeyondOriginalRecastTime>
      <HideSpellName>false</HideSpellName>
      <HideCounter>true</HideCounter>
      <IsCounterToCenter>false</IsCounterToCenter>
      <IsReverse>false</IsReverse>
      <MatchDateTime>0001-01-01T00:00:00</MatchDateTime>
      <UseHotbarRecastTime>false</UseHotbarRecastTime>
      <HotbarName />
      <ReduceIconBrightness>false</ReduceIconBrightness>
      <SpellIcon />
      <SpellIconSize>24</SpellIconSize>
      <IsNotResetAtWipeout>false</IsNotResetAtWipeout>
      <TimeupHide>false</TimeupHide>
      <ToInstance>false</ToInstance>
      <UpperLimitOfExtension>0</UpperLimitOfExtension>
      <BlinkTime>0</BlinkTime>
      <BlinkIcon>false</BlinkIcon>
      <BlinkBar>false</BlinkBar>
      <JobFilter />
      <PartyJobFilter />
      <PartyCompositionFilter />
      <ZoneFilter />
      <TimersMustRunningForStart />
      <TimersMustStoppingForStart />
      <ExpressionFilter>
        <expression />
        <expression />
        <expression />
        <expression />
      </ExpressionFilter>
      <IsSequentialTTS>false</IsSequentialTTS>
      <MatchTextToSpeak />
      <MatchAdvancedConfig>
        <IsEnabled>false</IsEnabled>
        <ToMainDevice>true</ToMainDevice>
        <ToSubDevice>false</ToSubDevice>
        <ToDicordTextChat>false</ToDicordTextChat>
        <Palette>Default</Palette>
      </MatchAdvancedConfig>
      <OverTime>0</OverTime>
      <OverTextToSpeak />
      <OverAdvancedConfig>
        <IsEnabled>false</IsEnabled>
        <ToMainDevice>true</ToMainDevice>
        <ToSubDevice>false</ToSubDevice>
        <ToDicordTextChat>false</ToDicordTextChat>
        <Palette>Default</Palette>
      </OverAdvancedConfig>
      <BeforeTime>0</BeforeTime>
      <BeforeTextToSpeak />
      <BeforeAdvancedConfig>
        <IsEnabled>false</IsEnabled>
        <ToMainDevice>true</ToMainDevice>
        <ToSubDevice>false</ToSubDevice>
        <ToDicordTextChat>false</ToDicordTextChat>
        <Palette>Default</Palette>
      </BeforeAdvancedConfig>
      <TimeupTextToSpeak />
      <TimeupAdvancedConfig>
        <IsEnabled>false</IsEnabled>
        <ToMainDevice>true</ToMainDevice>
        <ToSubDevice>false</ToSubDevice>
        <ToDicordTextChat>false</ToDicordTextChat>
        <Palette>Default</Palette>
      </TimeupAdvancedConfig>
      <MatchSound />
      <OverSound />
      <BeforeSound />
      <TimeupSound />
    </SpellTimer>
    <SpellTimer>
      <SortPriority>0</SortPriority>
      <IsChecked>false</IsChecked>
      <IsExpanded>false</IsExpanded>
      <Enabled>true</Enabled>
      <IsCircleStyle>false</IsCircleStyle>
      <TitleVerticalAlignmentInCircle>Center</TitleVerticalAlignmentInCircle>
      <Left>0</Left>
      <Top>0</Top>
      <ID>15</ID>
      <Guid>7e6a74fe-4140-42d4-b76d-5e3c2830b256</Guid>
      <PanelID>f27167af-218a-483a-981f-ff479a9d612d</PanelID>
      <Panel>02_ult_VS_Bahamut-Nael Words</Panel>
      <SpellTitle>　ランダム1名にAoE,⇒外周安置</SpellTitle>
      <RegexEnabled>false</RegexEnabled>
      <Keyword>我、舞い降りて 鉄の覇道を征く！</Keyword>
      <RecastTime>10</RecastTime>
      <DelayToShow>0</DelayToShow>
      <RecastTimeExtending1>0</RecastTimeExtending1>
      <RecastTimeExtending2>0</RecastTimeExtending2>
      <RecastTimeExtending3>0</RecastTimeExtending3>
      <OverlapRecastTime>false</OverlapRecastTime>
      <IsNotResetBarOnExtended>false</IsNotResetBarOnExtended>
      <ProgressBarVisible>true</ProgressBarVisible>
      <Font FontFamily="Yu Gothic UI" Size="30" Stretch="Normal" Style="Normal" Weight="Bold" />
      <FontColor>#DC143C</FontColor>
      <FontOutlineColor>#FFFFFF</FontOutlineColor>
      <WarningTime>0</WarningTime>
      <ChangeFontColorsWhenWarning>false</ChangeFontColorsWhenWarning>
      <WarningFontColor>#FFFFFF</WarningFontColor>
      <WarningFontOutlineColor>#FF4500</WarningFontOutlineColor>
      <ChangeFontColorWhenContainsMe>false</ChangeFontColorWhenContainsMe>
      <BarWidth>285</BarWidth>
      <BarHeight>0</BarHeight>
      <BarColor>#FFFFFF</BarColor>
      <BarOutlineColor>#191970</BarOutlineColor>
      <BarBlurRadius>11</BarBlurRadius>
      <BackgroundColor>#FFFFFF</BackgroundColor>
      <BackgroundAlpha>0</BackgroundAlpha>
      <DisplayNo>105</DisplayNo>
      <DontHide>false</DontHide>
      <IsHideInNotCombat>false</IsHideInNotCombat>
      <ExtendBeyondOriginalRecastTime>false</ExtendBeyondOriginalRecastTime>
      <HideSpellName>false</HideSpellName>
      <HideCounter>true</HideCounter>
      <IsCounterToCenter>false</IsCounterToCenter>
      <IsReverse>false</IsReverse>
      <MatchDateTime>0001-01-01T00:00:00</MatchDateTime>
      <UseHotbarRecastTime>false</UseHotbarRecastTime>
      <HotbarName />
      <ReduceIconBrightness>false</ReduceIconBrightness>
      <SpellIcon />
      <SpellIconSize>24</SpellIconSize>
      <IsNotResetAtWipeout>false</IsNotResetAtWipeout>
      <TimeupHide>false</TimeupHide>
      <ToInstance>false</ToInstance>
      <UpperLimitOfExtension>0</UpperLimitOfExtension>
      <BlinkTime>0</BlinkTime>
      <BlinkIcon>false</BlinkIcon>
      <BlinkBar>false</BlinkBar>
      <JobFilter />
      <PartyJobFilter />
      <PartyCompositionFilter />
      <ZoneFilter />
      <TimersMustRunningForStart />
      <TimersMustStoppingForStart />
      <ExpressionFilter>
        <expression />
        <expression />
        <expression />
        <expression />
      </ExpressionFilter>
      <IsSequentialTTS>false</IsSequentialTTS>
      <MatchTextToSpeak />
      <MatchAdvancedConfig>
        <IsEnabled>false</IsEnabled>
        <ToMainDevice>true</ToMainDevice>
        <ToSubDevice>false</ToSubDevice>
        <ToDicordTextChat>false</ToDicordTextChat>
        <Palette>Default</Palette>
      </MatchAdvancedConfig>
      <OverTime>0</OverTime>
      <OverTextToSpeak />
      <OverAdvancedConfig>
        <IsEnabled>false</IsEnabled>
        <ToMainDevice>true</ToMainDevice>
        <ToSubDevice>false</ToSubDevice>
        <ToDicordTextChat>false</ToDicordTextChat>
        <Palette>Default</Palette>
      </OverAdvancedConfig>
      <BeforeTime>0</BeforeTime>
      <BeforeTextToSpeak />
      <BeforeAdvancedConfig>
        <IsEnabled>false</IsEnabled>
        <ToMainDevice>true</ToMainDevice>
        <ToSubDevice>false</ToSubDevice>
        <ToDicordTextChat>false</ToDicordTextChat>
        <Palette>Default</Palette>
      </BeforeAdvancedConfig>
      <TimeupTextToSpeak />
      <TimeupAdvancedConfig>
        <IsEnabled>false</IsEnabled>
        <ToMainDevice>true</ToMainDevice>
        <ToSubDevice>false</ToSubDevice>
        <ToDicordTextChat>false</ToDicordTextChat>
        <Palette>Default</Palette>
      </TimeupAdvancedConfig>
      <MatchSound />
      <OverSound />
      <BeforeSound />
      <TimeupSound />
    </SpellTimer>
    <SpellTimer>
      <SortPriority>0</SortPriority>
      <IsChecked>false</IsChecked>
      <IsExpanded>false</IsExpanded>
      <Enabled>true</Enabled>
      <IsCircleStyle>false</IsCircleStyle>
      <TitleVerticalAlignmentInCircle>Center</TitleVerticalAlignmentInCircle>
      <Left>0</Left>
      <Top>0</Top>
      <ID>16</ID>
      <Guid>5b000ff4-716f-4511-b03a-67dbb5c656ce</Guid>
      <PanelID>f27167af-218a-483a-981f-ff479a9d612d</PanelID>
      <Panel>02_ult_VS_Bahamut-Nael Words</Panel>
      <SpellTitle>　対象者にDot付AoE,⇒散開,⇒ヘイト1位AoE</SpellTitle>
      <RegexEnabled>false</RegexEnabled>
      <Keyword>超新星よ、輝きを増せ！ 星降りの夜に、紅月を称えよ！</Keyword>
      <RecastTime>10</RecastTime>
      <DelayToShow>0</DelayToShow>
      <RecastTimeExtending1>0</RecastTimeExtending1>
      <RecastTimeExtending2>0</RecastTimeExtending2>
      <RecastTimeExtending3>0</RecastTimeExtending3>
      <OverlapRecastTime>false</OverlapRecastTime>
      <IsNotResetBarOnExtended>false</IsNotResetBarOnExtended>
      <ProgressBarVisible>true</ProgressBarVisible>
      <Font FontFamily="Yu Gothic UI" Size="30" Stretch="Normal" Style="Normal" Weight="Bold" />
      <FontColor>#DC143C</FontColor>
      <FontOutlineColor>#FFFFFF</FontOutlineColor>
      <WarningTime>0</WarningTime>
      <ChangeFontColorsWhenWarning>false</ChangeFontColorsWhenWarning>
      <WarningFontColor>#FFFFFF</WarningFontColor>
      <WarningFontOutlineColor>#FF4500</WarningFontOutlineColor>
      <ChangeFontColorWhenContainsMe>false</ChangeFontColorWhenContainsMe>
      <BarWidth>285</BarWidth>
      <BarHeight>0</BarHeight>
      <BarColor>#FFFFFF</BarColor>
      <BarOutlineColor>#191970</BarOutlineColor>
      <BarBlurRadius>11</BarBlurRadius>
      <BackgroundColor>#FFFFFF</BackgroundColor>
      <BackgroundAlpha>0</BackgroundAlpha>
      <DisplayNo>106</DisplayNo>
      <DontHide>false</DontHide>
      <IsHideInNotCombat>false</IsHideInNotCombat>
      <ExtendBeyondOriginalRecastTime>false</ExtendBeyondOriginalRecastTime>
      <HideSpellName>false</HideSpellName>
      <HideCounter>true</HideCounter>
      <IsCounterToCenter>false</IsCounterToCenter>
      <IsReverse>false</IsReverse>
      <MatchDateTime>0001-01-01T00:00:00</MatchDateTime>
      <UseHotbarRecastTime>false</UseHotbarRecastTime>
      <HotbarName />
      <ReduceIconBrightness>false</ReduceIconBrightness>
      <SpellIcon />
      <SpellIconSize>24</SpellIconSize>
      <IsNotResetAtWipeout>false</IsNotResetAtWipeout>
      <TimeupHide>false</TimeupHide>
      <ToInstance>false</ToInstance>
      <UpperLimitOfExtension>0</UpperLimitOfExtension>
      <BlinkTime>0</BlinkTime>
      <BlinkIcon>false</BlinkIcon>
      <BlinkBar>false</BlinkBar>
      <JobFilter />
      <PartyJobFilter />
      <PartyCompositionFilter />
      <ZoneFilter />
      <TimersMustRunningForStart />
      <TimersMustStoppingForStart />
      <ExpressionFilter>
        <expression />
        <expression />
        <expression />
        <expression />
      </ExpressionFilter>
      <IsSequentialTTS>false</IsSequentialTTS>
      <MatchTextToSpeak />
      <MatchAdvancedConfig>
        <IsEnabled>false</IsEnabled>
        <ToMainDevice>true</ToMainDevice>
        <ToSubDevice>false</ToSubDevice>
        <ToDicordTextChat>false</ToDicordTextChat>
        <Palette>Default</Palette>
      </MatchAdvancedConfig>
      <OverTime>0</OverTime>
      <OverTextToSpeak />
      <OverAdvancedConfig>
        <IsEnabled>false</IsEnabled>
        <ToMainDevice>true</ToMainDevice>
        <ToSubDevice>false</ToSubDevice>
        <ToDicordTextChat>false</ToDicordTextChat>
        <Palette>Default</Palette>
      </OverAdvancedConfig>
      <BeforeTime>0</BeforeTime>
      <BeforeTextToSpeak />
      <BeforeAdvancedConfig>
        <IsEnabled>false</IsEnabled>
        <ToMainDevice>true</ToMainDevice>
        <ToSubDevice>false</ToSubDevice>
        <ToDicordTextChat>false</ToDicordTextChat>
        <Palette>Default</Palette>
      </BeforeAdvancedConfig>
      <TimeupTextToSpeak />
      <TimeupAdvancedConfig>
        <IsEnabled>false</IsEnabled>
        <ToMainDevice>true</ToMainDevice>
        <ToSubDevice>false</ToSubDevice>
        <ToDicordTextChat>false</ToDicordTextChat>
        <Palette>Default</Palette>
      </TimeupAdvancedConfig>
      <MatchSound />
      <OverSound />
      <BeforeSound />
      <TimeupSound />
    </SpellTimer>
    <SpellTimer>
      <SortPriority>0</SortPriority>
      <IsChecked>false</IsChecked>
      <IsExpanded>false</IsExpanded>
      <Enabled>true</Enabled>
      <IsCircleStyle>false</IsCircleStyle>
      <TitleVerticalAlignmentInCircle>Center</TitleVerticalAlignmentInCircle>
      <Left>0</Left>
      <Top>0</Top>
      <ID>17</ID>
      <Guid>f1afc6f6-a8b0-4153-ac85-2dd0c72df5c5</Guid>
      <PanelID>f27167af-218a-483a-981f-ff479a9d612d</PanelID>
      <Panel>02_ult_VS_Bahamut-Nael Words</Panel>
      <SpellTitle>　対象者にDot付AoE,⇒ヘイト1位AoE,⇒頭割</SpellTitle>
      <RegexEnabled>false</RegexEnabled>
      <Keyword>超新星よ、輝きを増せ！ 紅月下の赤熱せし地を照らせ！</Keyword>
      <RecastTime>10</RecastTime>
      <DelayToShow>0</DelayToShow>
      <RecastTimeExtending1>0</RecastTimeExtending1>
      <RecastTimeExtending2>0</RecastTimeExtending2>
      <RecastTimeExtending3>0</RecastTimeExtending3>
      <OverlapRecastTime>false</OverlapRecastTime>
      <IsNotResetBarOnExtended>false</IsNotResetBarOnExtended>
      <ProgressBarVisible>true</ProgressBarVisible>
      <Font FontFamily="Yu Gothic UI" Size="30" Stretch="Normal" Style="Normal" Weight="Bold" />
      <FontColor>#DC143C</FontColor>
      <FontOutlineColor>#FFFFFF</FontOutlineColor>
      <WarningTime>0</WarningTime>
      <ChangeFontColorsWhenWarning>false</ChangeFontColorsWhenWarning>
      <WarningFontColor>#FFFFFF</WarningFontColor>
      <WarningFontOutlineColor>#FF4500</WarningFontOutlineColor>
      <ChangeFontColorWhenContainsMe>false</ChangeFontColorWhenContainsMe>
      <BarWidth>285</BarWidth>
      <BarHeight>0</BarHeight>
      <BarColor>#FFFFFF</BarColor>
      <BarOutlineColor>#191970</BarOutlineColor>
      <BarBlurRadius>11</BarBlurRadius>
      <BackgroundColor>#FFFFFF</BackgroundColor>
      <BackgroundAlpha>0</BackgroundAlpha>
      <DisplayNo>107</DisplayNo>
      <DontHide>false</DontHide>
      <IsHideInNotCombat>false</IsHideInNotCombat>
      <ExtendBeyondOriginalRecastTime>false</ExtendBeyondOriginalRecastTime>
      <HideSpellName>false</HideSpellName>
      <HideCounter>true</HideCounter>
      <IsCounterToCenter>false</IsCounterToCenter>
      <IsReverse>false</IsReverse>
      <MatchDateTime>0001-01-01T00:00:00</MatchDateTime>
      <UseHotbarRecastTime>false</UseHotbarRecastTime>
      <HotbarName />
      <ReduceIconBrightness>false</ReduceIconBrightness>
      <SpellIcon />
      <SpellIconSize>24</SpellIconSize>
      <IsNotResetAtWipeout>false</IsNotResetAtWipeout>
      <TimeupHide>false</TimeupHide>
      <ToInstance>false</ToInstance>
      <UpperLimitOfExtension>0</UpperLimitOfExtension>
      <BlinkTime>0</BlinkTime>
      <BlinkIcon>false</BlinkIcon>
      <BlinkBar>false</BlinkBar>
      <JobFilter />
      <PartyJobFilter />
      <PartyCompositionFilter />
      <ZoneFilter />
      <TimersMustRunningForStart />
      <TimersMustStoppingForStart />
      <ExpressionFilter>
        <expression />
        <expression />
        <expression />
        <expression />
      </ExpressionFilter>
      <IsSequentialTTS>false</IsSequentialTTS>
      <MatchTextToSpeak />
      <MatchAdvancedConfig>
        <IsEnabled>false</IsEnabled>
        <ToMainDevice>true</ToMainDevice>
        <ToSubDevice>false</ToSubDevice>
        <ToDicordTextChat>false</ToDicordTextChat>
        <Palette>Default</Palette>
      </MatchAdvancedConfig>
      <OverTime>0</OverTime>
      <OverTextToSpeak />
      <OverAdvancedConfig>
        <IsEnabled>false</IsEnabled>
        <ToMainDevice>true</ToMainDevice>
        <ToSubDevice>false</ToSubDevice>
        <ToDicordTextChat>false</ToDicordTextChat>
        <Palette>Default</Palette>
      </OverAdvancedConfig>
      <BeforeTime>0</BeforeTime>
      <BeforeTextToSpeak />
      <BeforeAdvancedConfig>
        <IsEnabled>false</IsEnabled>
        <ToMainDevice>true</ToMainDevice>
        <ToSubDevice>false</ToSubDevice>
        <ToDicordTextChat>false</ToDicordTextChat>
        <Palette>Default</Palette>
      </BeforeAdvancedConfig>
      <TimeupTextToSpeak />
      <TimeupAdvancedConfig>
        <IsEnabled>false</IsEnabled>
        <ToMainDevice>true</ToMainDevice>
        <ToSubDevice>false</ToSubDevice>
        <ToDicordTextChat>false</ToDicordTextChat>
        <Palette>Default</Palette>
      </TimeupAdvancedConfig>
      <MatchSound />
      <OverSound />
      <BeforeSound />
      <TimeupSound />
    </SpellTimer>
    <SpellTimer>
      <SortPriority>0</SortPriority>
      <IsChecked>false</IsChecked>
      <IsExpanded>false</IsExpanded>
      <Enabled>true</Enabled>
      <IsCircleStyle>false</IsCircleStyle>
      <TitleVerticalAlignmentInCircle>Center</TitleVerticalAlignmentInCircle>
      <Left>0</Left>
      <Top>0</Top>
      <ID>2</ID>
      <Guid>6c1e76a9-e2e9-4584-8a46-8fe6438f4124</Guid>
      <PanelID>9f50e2b1-8283-4e6e-96c2-d584b0c8765a</PanelID>
      <Panel>02_ult_VS_Bahamut-Neal Chain Lightning</Panel>
      <SpellTitle>WAR</SpellTitle>
      <RegexEnabled>true</RegexEnabled>
      <Keyword>&lt;WAR&gt; gains the effect of サンダーウィング</Keyword>
      <RecastTime>5</RecastTime>
      <DelayToShow>0</DelayToShow>
      <RecastTimeExtending1>0</RecastTimeExtending1>
      <RecastTimeExtending2>0</RecastTimeExtending2>
      <RecastTimeExtending3>0</RecastTimeExtending3>
      <OverlapRecastTime>true</OverlapRecastTime>
      <IsNotResetBarOnExtended>false</IsNotResetBarOnExtended>
      <ProgressBarVisible>true</ProgressBarVisible>
      <Font FontFamily="Arial" Size="11" Stretch="Normal" Style="Normal" Weight="Normal" />
      <FontColor>#DC143C</FontColor>
      <FontOutlineColor>#191970</FontOutlineColor>
      <WarningTime>0</WarningTime>
      <ChangeFontColorsWhenWarning>false</ChangeFontColorsWhenWarning>
      <WarningFontColor>#FFFFFF</WarningFontColor>
      <WarningFontOutlineColor>#FF4500</WarningFontOutlineColor>
      <ChangeFontColorWhenContainsMe>false</ChangeFontColorWhenContainsMe>
      <BarWidth>0</BarWidth>
      <BarHeight>0</BarHeight>
      <BarColor>#FFFFFF</BarColor>
      <BarOutlineColor>#191970</BarOutlineColor>
      <BarBlurRadius>11</BarBlurRadius>
      <BackgroundColor>#FFFFFF</BackgroundColor>
      <BackgroundAlpha>0</BackgroundAlpha>
      <DisplayNo>1</DisplayNo>
      <DontHide>false</DontHide>
      <IsHideInNotCombat>false</IsHideInNotCombat>
      <ExtendBeyondOriginalRecastTime>false</ExtendBeyondOriginalRecastTime>
      <HideSpellName>true</HideSpellName>
      <HideCounter>true</HideCounter>
      <IsCounterToCenter>false</IsCounterToCenter>
      <IsReverse>false</IsReverse>
      <MatchDateTime>0001-01-01T00:00:00</MatchDateTime>
      <UseHotbarRecastTime>false</UseHotbarRecastTime>
      <HotbarName />
      <ReduceIconBrightness>false</ReduceIconBrightness>
      <SpellIcon>WAR.png</SpellIcon>
      <SpellIconSize>64</SpellIconSize>
      <IsNotResetAtWipeout>false</IsNotResetAtWipeout>
      <TimeupHide>false</TimeupHide>
      <ToInstance>false</ToInstance>
      <UpperLimitOfExtension>0</UpperLimitOfExtension>
      <BlinkTime>0</BlinkTime>
      <BlinkIcon>false</BlinkIcon>
      <BlinkBar>false</BlinkBar>
      <JobFilter />
      <PartyJobFilter />
      <PartyCompositionFilter />
      <ZoneFilter />
      <TimersMustRunningForStart />
      <TimersMustStoppingForStart />
      <ExpressionFilter>
        <expression />
        <expression />
        <expression />
        <expression />
      </ExpressionFilter>
      <IsSequentialTTS>false</IsSequentialTTS>
      <MatchTextToSpeak />
      <MatchAdvancedConfig>
        <IsEnabled>false</IsEnabled>
        <ToMainDevice>true</ToMainDevice>
        <ToSubDevice>false</ToSubDevice>
        <ToDicordTextChat>false</ToDicordTextChat>
        <Palette>Default</Palette>
      </MatchAdvancedConfig>
      <OverTime>0</OverTime>
      <OverTextToSpeak />
      <OverAdvancedConfig>
        <IsEnabled>false</IsEnabled>
        <ToMainDevice>true</ToMainDevice>
        <ToSubDevice>false</ToSubDevice>
        <ToDicordTextChat>false</ToDicordTextChat>
        <Palette>Default</Palette>
      </OverAdvancedConfig>
      <BeforeTime>0</BeforeTime>
      <BeforeTextToSpeak />
      <BeforeAdvancedConfig>
        <IsEnabled>false</IsEnabled>
        <ToMainDevice>true</ToMainDevice>
        <ToSubDevice>false</ToSubDevice>
        <ToDicordTextChat>false</ToDicordTextChat>
        <Palette>Default</Palette>
      </BeforeAdvancedConfig>
      <TimeupTextToSpeak />
      <TimeupAdvancedConfig>
        <IsEnabled>false</IsEnabled>
        <ToMainDevice>true</ToMainDevice>
        <ToSubDevice>false</ToSubDevice>
        <ToDicordTextChat>false</ToDicordTextChat>
        <Palette>Default</Palette>
      </TimeupAdvancedConfig>
      <MatchSound />
      <OverSound />
      <BeforeSound />
      <TimeupSound />
    </SpellTimer>
    <SpellTimer>
      <SortPriority>0</SortPriority>
      <IsChecked>false</IsChecked>
      <IsExpanded>false</IsExpanded>
      <Enabled>true</Enabled>
      <IsCircleStyle>false</IsCircleStyle>
      <TitleVerticalAlignmentInCircle>Center</TitleVerticalAlignmentInCircle>
      <Left>0</Left>
      <Top>0</Top>
      <ID>3</ID>
      <Guid>03c20860-fdfe-4b89-8954-f86b33aae29e</Guid>
      <PanelID>9f50e2b1-8283-4e6e-96c2-d584b0c8765a</PanelID>
      <Panel>02_ult_VS_Bahamut-Neal Chain Lightning</Panel>
      <SpellTitle>PLD</SpellTitle>
      <RegexEnabled>true</RegexEnabled>
      <Keyword>&lt;PLD&gt; gains the effect of サンダーウィング</Keyword>
      <RecastTime>5</RecastTime>
      <DelayToShow>0</DelayToShow>
      <RecastTimeExtending1>0</RecastTimeExtending1>
      <RecastTimeExtending2>0</RecastTimeExtending2>
      <RecastTimeExtending3>0</RecastTimeExtending3>
      <OverlapRecastTime>true</OverlapRecastTime>
      <IsNotResetBarOnExtended>false</IsNotResetBarOnExtended>
      <ProgressBarVisible>true</ProgressBarVisible>
      <Font FontFamily="Arial" Size="11" Stretch="Normal" Style="Normal" Weight="Normal" />
      <FontColor>#DC143C</FontColor>
      <FontOutlineColor>#191970</FontOutlineColor>
      <WarningTime>0</WarningTime>
      <ChangeFontColorsWhenWarning>false</ChangeFontColorsWhenWarning>
      <WarningFontColor>#FFFFFF</WarningFontColor>
      <WarningFontOutlineColor>#FF4500</WarningFontOutlineColor>
      <ChangeFontColorWhenContainsMe>false</ChangeFontColorWhenContainsMe>
      <BarWidth>0</BarWidth>
      <BarHeight>0</BarHeight>
      <BarColor>#FFFFFF</BarColor>
      <BarOutlineColor>#191970</BarOutlineColor>
      <BarBlurRadius>11</BarBlurRadius>
      <BackgroundColor>#FFFFFF</BackgroundColor>
      <BackgroundAlpha>0</BackgroundAlpha>
      <DisplayNo>2</DisplayNo>
      <DontHide>false</DontHide>
      <IsHideInNotCombat>false</IsHideInNotCombat>
      <ExtendBeyondOriginalRecastTime>false</ExtendBeyondOriginalRecastTime>
      <HideSpellName>true</HideSpellName>
      <HideCounter>true</HideCounter>
      <IsCounterToCenter>false</IsCounterToCenter>
      <IsReverse>false</IsReverse>
      <MatchDateTime>0001-01-01T00:00:00</MatchDateTime>
      <UseHotbarRecastTime>false</UseHotbarRecastTime>
      <HotbarName />
      <ReduceIconBrightness>false</ReduceIconBrightness>
      <SpellIcon>PLD.png</SpellIcon>
      <SpellIconSize>64</SpellIconSize>
      <IsNotResetAtWipeout>false</IsNotResetAtWipeout>
      <TimeupHide>false</TimeupHide>
      <ToInstance>false</ToInstance>
      <UpperLimitOfExtension>0</UpperLimitOfExtension>
      <BlinkTime>0</BlinkTime>
      <BlinkIcon>false</BlinkIcon>
      <BlinkBar>false</BlinkBar>
      <JobFilter />
      <PartyJobFilter />
      <PartyCompositionFilter />
      <ZoneFilter />
      <TimersMustRunningForStart />
      <TimersMustStoppingForStart />
      <ExpressionFilter>
        <expression />
        <expression />
        <expression />
        <expression />
      </ExpressionFilter>
      <IsSequentialTTS>false</IsSequentialTTS>
      <MatchTextToSpeak />
      <MatchAdvancedConfig>
        <IsEnabled>false</IsEnabled>
        <ToMainDevice>true</ToMainDevice>
        <ToSubDevice>false</ToSubDevice>
        <ToDicordTextChat>false</ToDicordTextChat>
        <Palette>Default</Palette>
      </MatchAdvancedConfig>
      <OverTime>0</OverTime>
      <OverTextToSpeak />
      <OverAdvancedConfig>
        <IsEnabled>false</IsEnabled>
        <ToMainDevice>true</ToMainDevice>
        <ToSubDevice>false</ToSubDevice>
        <ToDicordTextChat>false</ToDicordTextChat>
        <Palette>Default</Palette>
      </OverAdvancedConfig>
      <BeforeTime>0</BeforeTime>
      <BeforeTextToSpeak />
      <BeforeAdvancedConfig>
        <IsEnabled>false</IsEnabled>
        <ToMainDevice>true</ToMainDevice>
        <ToSubDevice>false</ToSubDevice>
        <ToDicordTextChat>false</ToDicordTextChat>
        <Palette>Default</Palette>
      </BeforeAdvancedConfig>
      <TimeupTextToSpeak />
      <TimeupAdvancedConfig>
        <IsEnabled>false</IsEnabled>
        <ToMainDevice>true</ToMainDevice>
        <ToSubDevice>false</ToSubDevice>
        <ToDicordTextChat>false</ToDicordTextChat>
        <Palette>Default</Palette>
      </TimeupAdvancedConfig>
      <MatchSound />
      <OverSound />
      <BeforeSound />
      <TimeupSound />
    </SpellTimer>
    <SpellTimer>
      <SortPriority>0</SortPriority>
      <IsChecked>false</IsChecked>
      <IsExpanded>false</IsExpanded>
      <Enabled>true</Enabled>
      <IsCircleStyle>false</IsCircleStyle>
      <TitleVerticalAlignmentInCircle>Center</TitleVerticalAlignmentInCircle>
      <Left>0</Left>
      <Top>0</Top>
      <ID>4</ID>
      <Guid>0d9c9bfb-76d6-46d3-8733-ea6195d72eb4</Guid>
      <PanelID>9f50e2b1-8283-4e6e-96c2-d584b0c8765a</PanelID>
      <Panel>02_ult_VS_Bahamut-Neal Chain Lightning</Panel>
      <SpellTitle>AST</SpellTitle>
      <RegexEnabled>true</RegexEnabled>
      <Keyword>&lt;AST&gt; gains the effect of サンダーウィング</Keyword>
      <RecastTime>5</RecastTime>
      <DelayToShow>0</DelayToShow>
      <RecastTimeExtending1>0</RecastTimeExtending1>
      <RecastTimeExtending2>0</RecastTimeExtending2>
      <RecastTimeExtending3>0</RecastTimeExtending3>
      <OverlapRecastTime>true</OverlapRecastTime>
      <IsNotResetBarOnExtended>false</IsNotResetBarOnExtended>
      <ProgressBarVisible>true</ProgressBarVisible>
      <Font FontFamily="Arial" Size="11" Stretch="Normal" Style="Normal" Weight="Normal" />
      <FontColor>#DC143C</FontColor>
      <FontOutlineColor>#191970</FontOutlineColor>
      <WarningTime>0</WarningTime>
      <ChangeFontColorsWhenWarning>false</ChangeFontColorsWhenWarning>
      <WarningFontColor>#FFFFFF</WarningFontColor>
      <WarningFontOutlineColor>#FF4500</WarningFontOutlineColor>
      <ChangeFontColorWhenContainsMe>false</ChangeFontColorWhenContainsMe>
      <BarWidth>0</BarWidth>
      <BarHeight>0</BarHeight>
      <BarColor>#FFFFFF</BarColor>
      <BarOutlineColor>#191970</BarOutlineColor>
      <BarBlurRadius>11</BarBlurRadius>
      <BackgroundColor>#FFFFFF</BackgroundColor>
      <BackgroundAlpha>0</BackgroundAlpha>
      <DisplayNo>3</DisplayNo>
      <DontHide>false</DontHide>
      <IsHideInNotCombat>false</IsHideInNotCombat>
      <ExtendBeyondOriginalRecastTime>false</ExtendBeyondOriginalRecastTime>
      <HideSpellName>true</HideSpellName>
      <HideCounter>true</HideCounter>
      <IsCounterToCenter>false</IsCounterToCenter>
      <IsReverse>false</IsReverse>
      <MatchDateTime>0001-01-01T00:00:00</MatchDateTime>
      <UseHotbarRecastTime>false</UseHotbarRecastTime>
      <HotbarName />
      <ReduceIconBrightness>false</ReduceIconBrightness>
      <SpellIcon>AST.png</SpellIcon>
      <SpellIconSize>64</SpellIconSize>
      <IsNotResetAtWipeout>false</IsNotResetAtWipeout>
      <TimeupHide>false</TimeupHide>
      <ToInstance>false</ToInstance>
      <UpperLimitOfExtension>0</UpperLimitOfExtension>
      <BlinkTime>0</BlinkTime>
      <BlinkIcon>false</BlinkIcon>
      <BlinkBar>false</BlinkBar>
      <JobFilter />
      <PartyJobFilter />
      <PartyCompositionFilter />
      <ZoneFilter />
      <TimersMustRunningForStart />
      <TimersMustStoppingForStart />
      <ExpressionFilter>
        <expression />
        <expression />
        <expression />
        <expression />
      </ExpressionFilter>
      <IsSequentialTTS>false</IsSequentialTTS>
      <MatchTextToSpeak />
      <MatchAdvancedConfig>
        <IsEnabled>false</IsEnabled>
        <ToMainDevice>true</ToMainDevice>
        <ToSubDevice>false</ToSubDevice>
        <ToDicordTextChat>false</ToDicordTextChat>
        <Palette>Default</Palette>
      </MatchAdvancedConfig>
      <OverTime>0</OverTime>
      <OverTextToSpeak />
      <OverAdvancedConfig>
        <IsEnabled>false</IsEnabled>
        <ToMainDevice>true</ToMainDevice>
        <ToSubDevice>false</ToSubDevice>
        <ToDicordTextChat>false</ToDicordTextChat>
        <Palette>Default</Palette>
      </OverAdvancedConfig>
      <BeforeTime>0</BeforeTime>
      <BeforeTextToSpeak />
      <BeforeAdvancedConfig>
        <IsEnabled>false</IsEnabled>
        <ToMainDevice>true</ToMainDevice>
        <ToSubDevice>false</ToSubDevice>
        <ToDicordTextChat>false</ToDicordTextChat>
        <Palette>Default</Palette>
      </BeforeAdvancedConfig>
      <TimeupTextToSpeak />
      <TimeupAdvancedConfig>
        <IsEnabled>false</IsEnabled>
        <ToMainDevice>true</ToMainDevice>
        <ToSubDevice>false</ToSubDevice>
        <ToDicordTextChat>false</ToDicordTextChat>
        <Palette>Default</Palette>
      </TimeupAdvancedConfig>
      <MatchSound />
      <OverSound />
      <BeforeSound />
      <TimeupSound />
    </SpellTimer>
    <SpellTimer>
      <SortPriority>0</SortPriority>
      <IsChecked>false</IsChecked>
      <IsExpanded>false</IsExpanded>
      <Enabled>true</Enabled>
      <IsCircleStyle>false</IsCircleStyle>
      <TitleVerticalAlignmentInCircle>Center</TitleVerticalAlignmentInCircle>
      <Left>0</Left>
      <Top>0</Top>
      <ID>5</ID>
      <Guid>18c4bc42-b736-4b20-8efa-058ab61cd71c</Guid>
      <PanelID>9f50e2b1-8283-4e6e-96c2-d584b0c8765a</PanelID>
      <Panel>02_ult_VS_Bahamut-Neal Chain Lightning</Panel>
      <SpellTitle>SCH</SpellTitle>
      <RegexEnabled>true</RegexEnabled>
      <Keyword>&lt;SCH&gt; gains the effect of サンダーウィング</Keyword>
      <RecastTime>5</RecastTime>
      <DelayToShow>0</DelayToShow>
      <RecastTimeExtending1>0</RecastTimeExtending1>
      <RecastTimeExtending2>0</RecastTimeExtending2>
      <RecastTimeExtending3>0</RecastTimeExtending3>
      <OverlapRecastTime>true</OverlapRecastTime>
      <IsNotResetBarOnExtended>false</IsNotResetBarOnExtended>
      <ProgressBarVisible>true</ProgressBarVisible>
      <Font FontFamily="Arial" Size="11" Stretch="Normal" Style="Normal" Weight="Normal" />
      <FontColor>#DC143C</FontColor>
      <FontOutlineColor>#191970</FontOutlineColor>
      <WarningTime>0</WarningTime>
      <ChangeFontColorsWhenWarning>false</ChangeFontColorsWhenWarning>
      <WarningFontColor>#FFFFFF</WarningFontColor>
      <WarningFontOutlineColor>#FF4500</WarningFontOutlineColor>
      <ChangeFontColorWhenContainsMe>false</ChangeFontColorWhenContainsMe>
      <BarWidth>0</BarWidth>
      <BarHeight>0</BarHeight>
      <BarColor>#FFFFFF</BarColor>
      <BarOutlineColor>#191970</BarOutlineColor>
      <BarBlurRadius>11</BarBlurRadius>
      <BackgroundColor>#FFFFFF</BackgroundColor>
      <BackgroundAlpha>0</BackgroundAlpha>
      <DisplayNo>4</DisplayNo>
      <DontHide>false</DontHide>
      <IsHideInNotCombat>false</IsHideInNotCombat>
      <ExtendBeyondOriginalRecastTime>false</ExtendBeyondOriginalRecastTime>
      <HideSpellName>true</HideSpellName>
      <HideCounter>true</HideCounter>
      <IsCounterToCenter>false</IsCounterToCenter>
      <IsReverse>false</IsReverse>
      <MatchDateTime>0001-01-01T00:00:00</MatchDateTime>
      <UseHotbarRecastTime>false</UseHotbarRecastTime>
      <HotbarName />
      <ReduceIconBrightness>false</ReduceIconBrightness>
      <SpellIcon>SCH.png</SpellIcon>
      <SpellIconSize>64</SpellIconSize>
      <IsNotResetAtWipeout>false</IsNotResetAtWipeout>
      <TimeupHide>false</TimeupHide>
      <ToInstance>false</ToInstance>
      <UpperLimitOfExtension>0</UpperLimitOfExtension>
      <BlinkTime>0</BlinkTime>
      <BlinkIcon>false</BlinkIcon>
      <BlinkBar>false</BlinkBar>
      <JobFilter />
      <PartyJobFilter />
      <PartyCompositionFilter />
      <ZoneFilter />
      <TimersMustRunningForStart />
      <TimersMustStoppingForStart />
      <ExpressionFilter>
        <expression />
        <expression />
        <expression />
        <expression />
      </ExpressionFilter>
      <IsSequentialTTS>false</IsSequentialTTS>
      <MatchTextToSpeak />
      <MatchAdvancedConfig>
        <IsEnabled>false</IsEnabled>
        <ToMainDevice>true</ToMainDevice>
        <ToSubDevice>false</ToSubDevice>
        <ToDicordTextChat>false</ToDicordTextChat>
        <Palette>Default</Palette>
      </MatchAdvancedConfig>
      <OverTime>0</OverTime>
      <OverTextToSpeak />
      <OverAdvancedConfig>
        <IsEnabled>false</IsEnabled>
        <ToMainDevice>true</ToMainDevice>
        <ToSubDevice>false</ToSubDevice>
        <ToDicordTextChat>false</ToDicordTextChat>
        <Palette>Default</Palette>
      </OverAdvancedConfig>
      <BeforeTime>0</BeforeTime>
      <BeforeTextToSpeak />
      <BeforeAdvancedConfig>
        <IsEnabled>false</IsEnabled>
        <ToMainDevice>true</ToMainDevice>
        <ToSubDevice>false</ToSubDevice>
        <ToDicordTextChat>false</ToDicordTextChat>
        <Palette>Default</Palette>
      </BeforeAdvancedConfig>
      <TimeupTextToSpeak />
      <TimeupAdvancedConfig>
        <IsEnabled>false</IsEnabled>
        <ToMainDevice>true</ToMainDevice>
        <ToSubDevice>false</ToSubDevice>
        <ToDicordTextChat>false</ToDicordTextChat>
        <Palette>Default</Palette>
      </TimeupAdvancedConfig>
      <MatchSound />
      <OverSound />
      <BeforeSound />
      <TimeupSound />
    </SpellTimer>
    <SpellTimer>
      <SortPriority>0</SortPriority>
      <IsChecked>false</IsChecked>
      <IsExpanded>false</IsExpanded>
      <Enabled>true</Enabled>
      <IsCircleStyle>false</IsCircleStyle>
      <TitleVerticalAlignmentInCircle>Center</TitleVerticalAlignmentInCircle>
      <Left>0</Left>
      <Top>0</Top>
      <ID>6</ID>
      <Guid>111252ae-075c-48bc-8a8f-c6d23068de1f</Guid>
      <PanelID>9f50e2b1-8283-4e6e-96c2-d584b0c8765a</PanelID>
      <Panel>02_ult_VS_Bahamut-Neal Chain Lightning</Panel>
      <SpellTitle>GNB</SpellTitle>
      <RegexEnabled>true</RegexEnabled>
      <Keyword>&lt;GNB&gt; gains the effect of サンダーウィング</Keyword>
      <RecastTime>5</RecastTime>
      <DelayToShow>0</DelayToShow>
      <RecastTimeExtending1>0</RecastTimeExtending1>
      <RecastTimeExtending2>0</RecastTimeExtending2>
      <RecastTimeExtending3>0</RecastTimeExtending3>
      <OverlapRecastTime>true</OverlapRecastTime>
      <IsNotResetBarOnExtended>false</IsNotResetBarOnExtended>
      <ProgressBarVisible>true</ProgressBarVisible>
      <Font FontFamily="Arial" Size="11" Stretch="Normal" Style="Normal" Weight="Normal" />
      <FontColor>#DC143C</FontColor>
      <FontOutlineColor>#191970</FontOutlineColor>
      <WarningTime>0</WarningTime>
      <ChangeFontColorsWhenWarning>false</ChangeFontColorsWhenWarning>
      <WarningFontColor>#FFFFFF</WarningFontColor>
      <WarningFontOutlineColor>#FF4500</WarningFontOutlineColor>
      <ChangeFontColorWhenContainsMe>false</ChangeFontColorWhenContainsMe>
      <BarWidth>0</BarWidth>
      <BarHeight>0</BarHeight>
      <BarColor>#FFFFFF</BarColor>
      <BarOutlineColor>#191970</BarOutlineColor>
      <BarBlurRadius>11</BarBlurRadius>
      <BackgroundColor>#FFFFFF</BackgroundColor>
      <BackgroundAlpha>0</BackgroundAlpha>
      <DisplayNo>5</DisplayNo>
      <DontHide>false</DontHide>
      <IsHideInNotCombat>false</IsHideInNotCombat>
      <ExtendBeyondOriginalRecastTime>false</ExtendBeyondOriginalRecastTime>
      <HideSpellName>true</HideSpellName>
      <HideCounter>true</HideCounter>
      <IsCounterToCenter>false</IsCounterToCenter>
      <IsReverse>false</IsReverse>
      <MatchDateTime>0001-01-01T00:00:00</MatchDateTime>
      <UseHotbarRecastTime>false</UseHotbarRecastTime>
      <HotbarName />
      <ReduceIconBrightness>false</ReduceIconBrightness>
      <SpellIcon>GNB.png</SpellIcon>
      <SpellIconSize>64</SpellIconSize>
      <IsNotResetAtWipeout>false</IsNotResetAtWipeout>
      <TimeupHide>false</TimeupHide>
      <ToInstance>false</ToInstance>
      <UpperLimitOfExtension>0</UpperLimitOfExtension>
      <BlinkTime>0</BlinkTime>
      <BlinkIcon>false</BlinkIcon>
      <BlinkBar>false</BlinkBar>
      <JobFilter />
      <PartyJobFilter />
      <PartyCompositionFilter />
      <ZoneFilter />
      <TimersMustRunningForStart />
      <TimersMustStoppingForStart />
      <ExpressionFilter>
        <expression />
        <expression />
        <expression />
        <expression />
      </ExpressionFilter>
      <IsSequentialTTS>false</IsSequentialTTS>
      <MatchTextToSpeak />
      <MatchAdvancedConfig>
        <IsEnabled>false</IsEnabled>
        <ToMainDevice>true</ToMainDevice>
        <ToSubDevice>false</ToSubDevice>
        <ToDicordTextChat>false</ToDicordTextChat>
        <Palette>Default</Palette>
      </MatchAdvancedConfig>
      <OverTime>0</OverTime>
      <OverTextToSpeak />
      <OverAdvancedConfig>
        <IsEnabled>false</IsEnabled>
        <ToMainDevice>true</ToMainDevice>
        <ToSubDevice>false</ToSubDevice>
        <ToDicordTextChat>false</ToDicordTextChat>
        <Palette>Default</Palette>
      </OverAdvancedConfig>
      <BeforeTime>0</BeforeTime>
      <BeforeTextToSpeak />
      <BeforeAdvancedConfig>
        <IsEnabled>false</IsEnabled>
        <ToMainDevice>true</ToMainDevice>
        <ToSubDevice>false</ToSubDevice>
        <ToDicordTextChat>false</ToDicordTextChat>
        <Palette>Default</Palette>
      </BeforeAdvancedConfig>
      <TimeupTextToSpeak />
      <TimeupAdvancedConfig>
        <IsEnabled>false</IsEnabled>
        <ToMainDevice>true</ToMainDevice>
        <ToSubDevice>false</ToSubDevice>
        <ToDicordTextChat>false</ToDicordTextChat>
        <Palette>Default</Palette>
      </TimeupAdvancedConfig>
      <MatchSound />
      <OverSound />
      <BeforeSound />
      <TimeupSound />
    </SpellTimer>
    <SpellTimer>
      <SortPriority>0</SortPriority>
      <IsChecked>false</IsChecked>
      <IsExpanded>false</IsExpanded>
      <Enabled>true</Enabled>
      <IsCircleStyle>false</IsCircleStyle>
      <TitleVerticalAlignmentInCircle>Center</TitleVerticalAlignmentInCircle>
      <Left>0</Left>
      <Top>0</Top>
      <ID>7</ID>
      <Guid>f79012a6-c537-4389-915a-1a77215b5295</Guid>
      <PanelID>9f50e2b1-8283-4e6e-96c2-d584b0c8765a</PanelID>
      <Panel>02_ult_VS_Bahamut-Neal Chain Lightning</Panel>
      <SpellTitle>DRG</SpellTitle>
      <RegexEnabled>true</RegexEnabled>
      <Keyword>&lt;DRG&gt; gains the effect of サンダーウィング</Keyword>
      <RecastTime>5</RecastTime>
      <DelayToShow>0</DelayToShow>
      <RecastTimeExtending1>0</RecastTimeExtending1>
      <RecastTimeExtending2>0</RecastTimeExtending2>
      <RecastTimeExtending3>0</RecastTimeExtending3>
      <OverlapRecastTime>true</OverlapRecastTime>
      <IsNotResetBarOnExtended>false</IsNotResetBarOnExtended>
      <ProgressBarVisible>true</ProgressBarVisible>
      <Font FontFamily="Arial" Size="11" Stretch="Normal" Style="Normal" Weight="Normal" />
      <FontColor>#DC143C</FontColor>
      <FontOutlineColor>#191970</FontOutlineColor>
      <WarningTime>0</WarningTime>
      <ChangeFontColorsWhenWarning>false</ChangeFontColorsWhenWarning>
      <WarningFontColor>#FFFFFF</WarningFontColor>
      <WarningFontOutlineColor>#FF4500</WarningFontOutlineColor>
      <ChangeFontColorWhenContainsMe>false</ChangeFontColorWhenContainsMe>
      <BarWidth>0</BarWidth>
      <BarHeight>0</BarHeight>
      <BarColor>#FFFFFF</BarColor>
      <BarOutlineColor>#191970</BarOutlineColor>
      <BarBlurRadius>11</BarBlurRadius>
      <BackgroundColor>#FFFFFF</BackgroundColor>
      <BackgroundAlpha>0</BackgroundAlpha>
      <DisplayNo>6</DisplayNo>
      <DontHide>false</DontHide>
      <IsHideInNotCombat>false</IsHideInNotCombat>
      <ExtendBeyondOriginalRecastTime>false</ExtendBeyondOriginalRecastTime>
      <HideSpellName>true</HideSpellName>
      <HideCounter>true</HideCounter>
      <IsCounterToCenter>false</IsCounterToCenter>
      <IsReverse>false</IsReverse>
      <MatchDateTime>0001-01-01T00:00:00</MatchDateTime>
      <UseHotbarRecastTime>false</UseHotbarRecastTime>
      <HotbarName />
      <ReduceIconBrightness>false</ReduceIconBrightness>
      <SpellIcon>DRG.png</SpellIcon>
      <SpellIconSize>64</SpellIconSize>
      <IsNotResetAtWipeout>false</IsNotResetAtWipeout>
      <TimeupHide>false</TimeupHide>
      <ToInstance>false</ToInstance>
      <UpperLimitOfExtension>0</UpperLimitOfExtension>
      <BlinkTime>0</BlinkTime>
      <BlinkIcon>false</BlinkIcon>
      <BlinkBar>false</BlinkBar>
      <JobFilter />
      <PartyJobFilter />
      <PartyCompositionFilter />
      <ZoneFilter />
      <TimersMustRunningForStart />
      <TimersMustStoppingForStart />
      <ExpressionFilter>
        <expression />
        <expression />
        <expression />
        <expression />
      </ExpressionFilter>
      <IsSequentialTTS>false</IsSequentialTTS>
      <MatchTextToSpeak>自分にサンダー</MatchTextToSpeak>
      <MatchAdvancedConfig>
        <IsEnabled>false</IsEnabled>
        <ToMainDevice>true</ToMainDevice>
        <ToSubDevice>false</ToSubDevice>
        <ToDicordTextChat>false</ToDicordTextChat>
        <Palette>Default</Palette>
      </MatchAdvancedConfig>
      <OverTime>0</OverTime>
      <OverTextToSpeak />
      <OverAdvancedConfig>
        <IsEnabled>false</IsEnabled>
        <ToMainDevice>true</ToMainDevice>
        <ToSubDevice>false</ToSubDevice>
        <ToDicordTextChat>false</ToDicordTextChat>
        <Palette>Default</Palette>
      </OverAdvancedConfig>
      <BeforeTime>0</BeforeTime>
      <BeforeTextToSpeak />
      <BeforeAdvancedConfig>
        <IsEnabled>false</IsEnabled>
        <ToMainDevice>true</ToMainDevice>
        <ToSubDevice>false</ToSubDevice>
        <ToDicordTextChat>false</ToDicordTextChat>
        <Palette>Default</Palette>
      </BeforeAdvancedConfig>
      <TimeupTextToSpeak />
      <TimeupAdvancedConfig>
        <IsEnabled>false</IsEnabled>
        <ToMainDevice>true</ToMainDevice>
        <ToSubDevice>false</ToSubDevice>
        <ToDicordTextChat>false</ToDicordTextChat>
        <Palette>Default</Palette>
      </TimeupAdvancedConfig>
      <MatchSound />
      <OverSound />
      <BeforeSound />
      <TimeupSound />
    </SpellTimer>
    <SpellTimer>
      <SortPriority>0</SortPriority>
      <IsChecked>false</IsChecked>
      <IsExpanded>false</IsExpanded>
      <Enabled>true</Enabled>
      <IsCircleStyle>false</IsCircleStyle>
      <TitleVerticalAlignmentInCircle>Center</TitleVerticalAlignmentInCircle>
      <Left>0</Left>
      <Top>0</Top>
      <ID>8</ID>
      <Guid>284a2293-f318-43df-b492-303ed0dfb967</Guid>
      <PanelID>9f50e2b1-8283-4e6e-96c2-d584b0c8765a</PanelID>
      <Panel>02_ult_VS_Bahamut-Neal Chain Lightning</Panel>
      <SpellTitle>MCH</SpellTitle>
      <RegexEnabled>true</RegexEnabled>
      <Keyword>&lt;MCH&gt; gains the effect of サンダーウィング</Keyword>
      <RecastTime>5</RecastTime>
      <DelayToShow>0</DelayToShow>
      <RecastTimeExtending1>0</RecastTimeExtending1>
      <RecastTimeExtending2>0</RecastTimeExtending2>
      <RecastTimeExtending3>0</RecastTimeExtending3>
      <OverlapRecastTime>true</OverlapRecastTime>
      <IsNotResetBarOnExtended>false</IsNotResetBarOnExtended>
      <ProgressBarVisible>true</ProgressBarVisible>
      <Font FontFamily="Arial" Size="11" Stretch="Normal" Style="Normal" Weight="Normal" />
      <FontColor>#DC143C</FontColor>
      <FontOutlineColor>#191970</FontOutlineColor>
      <WarningTime>0</WarningTime>
      <ChangeFontColorsWhenWarning>false</ChangeFontColorsWhenWarning>
      <WarningFontColor>#FFFFFF</WarningFontColor>
      <WarningFontOutlineColor>#FF4500</WarningFontOutlineColor>
      <ChangeFontColorWhenContainsMe>false</ChangeFontColorWhenContainsMe>
      <BarWidth>0</BarWidth>
      <BarHeight>0</BarHeight>
      <BarColor>#FFFFFF</BarColor>
      <BarOutlineColor>#191970</BarOutlineColor>
      <BarBlurRadius>11</BarBlurRadius>
      <BackgroundColor>#FFFFFF</BackgroundColor>
      <BackgroundAlpha>0</BackgroundAlpha>
      <DisplayNo>7</DisplayNo>
      <DontHide>false</DontHide>
      <IsHideInNotCombat>false</IsHideInNotCombat>
      <ExtendBeyondOriginalRecastTime>false</ExtendBeyondOriginalRecastTime>
      <HideSpellName>true</HideSpellName>
      <HideCounter>true</HideCounter>
      <IsCounterToCenter>false</IsCounterToCenter>
      <IsReverse>false</IsReverse>
      <MatchDateTime>0001-01-01T00:00:00</MatchDateTime>
      <UseHotbarRecastTime>false</UseHotbarRecastTime>
      <HotbarName />
      <ReduceIconBrightness>false</ReduceIconBrightness>
      <SpellIcon>MCH.png</SpellIcon>
      <SpellIconSize>64</SpellIconSize>
      <IsNotResetAtWipeout>false</IsNotResetAtWipeout>
      <TimeupHide>false</TimeupHide>
      <ToInstance>false</ToInstance>
      <UpperLimitOfExtension>0</UpperLimitOfExtension>
      <BlinkTime>0</BlinkTime>
      <BlinkIcon>false</BlinkIcon>
      <BlinkBar>false</BlinkBar>
      <JobFilter />
      <PartyJobFilter />
      <PartyCompositionFilter />
      <ZoneFilter />
      <TimersMustRunningForStart />
      <TimersMustStoppingForStart />
      <ExpressionFilter>
        <expression />
        <expression />
        <expression />
        <expression />
      </ExpressionFilter>
      <IsSequentialTTS>false</IsSequentialTTS>
      <MatchTextToSpeak />
      <MatchAdvancedConfig>
        <IsEnabled>false</IsEnabled>
        <ToMainDevice>true</ToMainDevice>
        <ToSubDevice>false</ToSubDevice>
        <ToDicordTextChat>false</ToDicordTextChat>
        <Palette>Default</Palette>
      </MatchAdvancedConfig>
      <OverTime>0</OverTime>
      <OverTextToSpeak />
      <OverAdvancedConfig>
        <IsEnabled>false</IsEnabled>
        <ToMainDevice>true</ToMainDevice>
        <ToSubDevice>false</ToSubDevice>
        <ToDicordTextChat>false</ToDicordTextChat>
        <Palette>Default</Palette>
      </OverAdvancedConfig>
      <BeforeTime>0</BeforeTime>
      <BeforeTextToSpeak />
      <BeforeAdvancedConfig>
        <IsEnabled>false</IsEnabled>
        <ToMainDevice>true</ToMainDevice>
        <ToSubDevice>false</ToSubDevice>
        <ToDicordTextChat>false</ToDicordTextChat>
        <Palette>Default</Palette>
      </BeforeAdvancedConfig>
      <TimeupTextToSpeak />
      <TimeupAdvancedConfig>
        <IsEnabled>false</IsEnabled>
        <ToMainDevice>true</ToMainDevice>
        <ToSubDevice>false</ToSubDevice>
        <ToDicordTextChat>false</ToDicordTextChat>
        <Palette>Default</Palette>
      </TimeupAdvancedConfig>
      <MatchSound />
      <OverSound />
      <BeforeSound />
      <TimeupSound />
    </SpellTimer>
    <SpellTimer>
      <SortPriority>0</SortPriority>
      <IsChecked>false</IsChecked>
      <IsExpanded>false</IsExpanded>
      <Enabled>true</Enabled>
      <IsCircleStyle>false</IsCircleStyle>
      <TitleVerticalAlignmentInCircle>Center</TitleVerticalAlignmentInCircle>
      <Left>0</Left>
      <Top>0</Top>
      <ID>9</ID>
      <Guid>4a7312e1-a3fa-4710-a94e-4c9d447455a3</Guid>
      <PanelID>9f50e2b1-8283-4e6e-96c2-d584b0c8765a</PanelID>
      <Panel>02_ult_VS_Bahamut-Neal Chain Lightning</Panel>
      <SpellTitle>RDM</SpellTitle>
      <RegexEnabled>true</RegexEnabled>
      <Keyword>&lt;RDM&gt; gains the effect of サンダーウィング</Keyword>
      <RecastTime>5</RecastTime>
      <DelayToShow>0</DelayToShow>
      <RecastTimeExtending1>0</RecastTimeExtending1>
      <RecastTimeExtending2>0</RecastTimeExtending2>
      <RecastTimeExtending3>0</RecastTimeExtending3>
      <OverlapRecastTime>true</OverlapRecastTime>
      <IsNotResetBarOnExtended>false</IsNotResetBarOnExtended>
      <ProgressBarVisible>true</ProgressBarVisible>
      <Font FontFamily="Arial" Size="11" Stretch="Normal" Style="Normal" Weight="Normal" />
      <FontColor>#DC143C</FontColor>
      <FontOutlineColor>#191970</FontOutlineColor>
      <WarningTime>0</WarningTime>
      <ChangeFontColorsWhenWarning>false</ChangeFontColorsWhenWarning>
      <WarningFontColor>#FFFFFF</WarningFontColor>
      <WarningFontOutlineColor>#FF4500</WarningFontOutlineColor>
      <ChangeFontColorWhenContainsMe>false</ChangeFontColorWhenContainsMe>
      <BarWidth>0</BarWidth>
      <BarHeight>0</BarHeight>
      <BarColor>#FFFFFF</BarColor>
      <BarOutlineColor>#191970</BarOutlineColor>
      <BarBlurRadius>11</BarBlurRadius>
      <BackgroundColor>#FFFFFF</BackgroundColor>
      <BackgroundAlpha>0</BackgroundAlpha>
      <DisplayNo>8</DisplayNo>
      <DontHide>false</DontHide>
      <IsHideInNotCombat>false</IsHideInNotCombat>
      <ExtendBeyondOriginalRecastTime>false</ExtendBeyondOriginalRecastTime>
      <HideSpellName>true</HideSpellName>
      <HideCounter>true</HideCounter>
      <IsCounterToCenter>false</IsCounterToCenter>
      <IsReverse>false</IsReverse>
      <MatchDateTime>0001-01-01T00:00:00</MatchDateTime>
      <UseHotbarRecastTime>false</UseHotbarRecastTime>
      <HotbarName />
      <ReduceIconBrightness>false</ReduceIconBrightness>
      <SpellIcon>RDM.png</SpellIcon>
      <SpellIconSize>64</SpellIconSize>
      <IsNotResetAtWipeout>false</IsNotResetAtWipeout>
      <TimeupHide>false</TimeupHide>
      <ToInstance>false</ToInstance>
      <UpperLimitOfExtension>0</UpperLimitOfExtension>
      <BlinkTime>0</BlinkTime>
      <BlinkIcon>false</BlinkIcon>
      <BlinkBar>false</BlinkBar>
      <JobFilter />
      <PartyJobFilter />
      <PartyCompositionFilter />
      <ZoneFilter />
      <TimersMustRunningForStart />
      <TimersMustStoppingForStart />
      <ExpressionFilter>
        <expression />
        <expression />
        <expression />
        <expression />
      </ExpressionFilter>
      <IsSequentialTTS>false</IsSequentialTTS>
      <MatchTextToSpeak />
      <MatchAdvancedConfig>
        <IsEnabled>false</IsEnabled>
        <ToMainDevice>true</ToMainDevice>
        <ToSubDevice>false</ToSubDevice>
        <ToDicordTextChat>false</ToDicordTextChat>
        <Palette>Default</Palette>
      </MatchAdvancedConfig>
      <OverTime>0</OverTime>
      <OverTextToSpeak />
      <OverAdvancedConfig>
        <IsEnabled>false</IsEnabled>
        <ToMainDevice>true</ToMainDevice>
        <ToSubDevice>false</ToSubDevice>
        <ToDicordTextChat>false</ToDicordTextChat>
        <Palette>Default</Palette>
      </OverAdvancedConfig>
      <BeforeTime>0</BeforeTime>
      <BeforeTextToSpeak />
      <BeforeAdvancedConfig>
        <IsEnabled>false</IsEnabled>
        <ToMainDevice>true</ToMainDevice>
        <ToSubDevice>false</ToSubDevice>
        <ToDicordTextChat>false</ToDicordTextChat>
        <Palette>Default</Palette>
      </BeforeAdvancedConfig>
      <TimeupTextToSpeak />
      <TimeupAdvancedConfig>
        <IsEnabled>false</IsEnabled>
        <ToMainDevice>true</ToMainDevice>
        <ToSubDevice>false</ToSubDevice>
        <ToDicordTextChat>false</ToDicordTextChat>
        <Palette>Default</Palette>
      </TimeupAdvancedConfig>
      <MatchSound />
      <OverSound />
      <BeforeSound />
      <TimeupSound />
    </SpellTimer>
  </Spells>
  <Tickers>
    <OnePointTelop>
      <SortPriority>0</SortPriority>
      <IsChecked>false</IsChecked>
      <IsExpanded>false</IsExpanded>
      <Enabled>true</Enabled>
      <ID>3</ID>
      <Guid>1f7d1b09-5118-428b-92fa-645f3af13f1f</Guid>
      <Left>1040</Left>
      <Top>630</Top>
      <Title>01_死の宣告1</Title>
      <Message>宣告１番{COUNT0}</Message>
      <RegexEnabled>true</RegexEnabled>
      <Keyword>&lt;mex&gt; gains the effect of 死の宣告 from  for 6.00 Seconds</Keyword>
      <Delay>0</Delay>
      <DisplayTime>6</DisplayTime>
      <Font FontFamily="Yu Gothic UI" Size="30" Stretch="Normal" Style="Normal" Weight="Normal" />
      <FontColor>#FFFFFF</FontColor>
      <FontOutlineColor>#DC143C</FontOutlineColor>
      <BarBlurRadius>14</BarBlurRadius>
      <BackgroundAlpha>0</BackgroundAlpha>
      <BackgroundColor>#FFFFFF</BackgroundColor>
      <AddMessageEnabled>false</AddMessageEnabled>
      <ProgressBarEnabled>true</ProgressBarEnabled>
      <JobFilter />
      <PartyJobFilter />
      <PartyCompositionFilter />
      <ZoneFilter>733</ZoneFilter>
      <TimersMustRunningForStart />
      <TimersMustStoppingForStart />
      <ExpressionFilter>
        <expression />
        <expression />
        <expression />
        <expression />
      </ExpressionFilter>
      <IsSequentialTTS>false</IsSequentialTTS>
      <MatchTextToSpeak />
      <DelayTextToSpeak />
      <MatchAdvancedConfig>
        <IsEnabled>false</IsEnabled>
        <ToMainDevice>true</ToMainDevice>
        <ToSubDevice>false</ToSubDevice>
        <ToDicordTextChat>false</ToDicordTextChat>
        <Palette>Default</Palette>
      </MatchAdvancedConfig>
      <DelayAdvancedConfig>
        <IsEnabled>false</IsEnabled>
        <ToMainDevice>true</ToMainDevice>
        <ToSubDevice>false</ToSubDevice>
        <ToDicordTextChat>false</ToDicordTextChat>
        <Palette>Default</Palette>
      </DelayAdvancedConfig>
      <DelaySound />
      <MatchSound />
    </OnePointTelop>
    <OnePointTelop>
      <SortPriority>0</SortPriority>
      <IsChecked>false</IsChecked>
      <IsExpanded>false</IsExpanded>
      <Enabled>true</Enabled>
      <ID>4</ID>
      <Guid>ba361790-b15e-4de9-839a-93406e2e9e6a</Guid>
      <Left>1040</Left>
      <Top>630</Top>
      <Title>01_死の宣告2</Title>
      <Message>宣告２番{COUNT0}</Message>
      <RegexEnabled>true</RegexEnabled>
      <Keyword>&lt;mex&gt; gains the effect of 死の宣告 from  for 10.00 Seconds</Keyword>
      <Delay>0</Delay>
      <DisplayTime>10</DisplayTime>
      <Font FontFamily="Yu Gothic UI" Size="30" Stretch="Normal" Style="Normal" Weight="Normal" />
      <FontColor>#FFFFFF</FontColor>
      <FontOutlineColor>#DC143C</FontOutlineColor>
      <BarBlurRadius>14</BarBlurRadius>
      <BackgroundAlpha>0</BackgroundAlpha>
      <BackgroundColor>#FFFFFF</BackgroundColor>
      <AddMessageEnabled>false</AddMessageEnabled>
      <ProgressBarEnabled>true</ProgressBarEnabled>
      <JobFilter />
      <PartyJobFilter />
      <PartyCompositionFilter />
      <ZoneFilter>733</ZoneFilter>
      <TimersMustRunningForStart />
      <TimersMustStoppingForStart />
      <ExpressionFilter>
        <expression />
        <expression />
        <expression />
        <expression />
      </ExpressionFilter>
      <IsSequentialTTS>false</IsSequentialTTS>
      <MatchTextToSpeak />
      <DelayTextToSpeak />
      <MatchAdvancedConfig>
        <IsEnabled>false</IsEnabled>
        <ToMainDevice>true</ToMainDevice>
        <ToSubDevice>false</ToSubDevice>
        <ToDicordTextChat>false</ToDicordTextChat>
        <Palette>Default</Palette>
      </MatchAdvancedConfig>
      <DelayAdvancedConfig>
        <IsEnabled>false</IsEnabled>
        <ToMainDevice>true</ToMainDevice>
        <ToSubDevice>false</ToSubDevice>
        <ToDicordTextChat>false</ToDicordTextChat>
        <Palette>Default</Palette>
      </DelayAdvancedConfig>
      <DelaySound />
      <MatchSound />
    </OnePointTelop>
    <OnePointTelop>
      <SortPriority>0</SortPriority>
      <IsChecked>false</IsChecked>
      <IsExpanded>false</IsExpanded>
      <Enabled>true</Enabled>
      <ID>5</ID>
      <Guid>f723c39e-0a2c-48e0-b35c-4920b2a518d9</Guid>
      <Left>1040</Left>
      <Top>630</Top>
      <Title>01_死の宣告3</Title>
      <Message>宣告３番{COUNT0}</Message>
      <RegexEnabled>true</RegexEnabled>
      <Keyword>&lt;mex&gt; gains the effect of 死の宣告 from  for 16.00 Seconds</Keyword>
      <Delay>0</Delay>
      <DisplayTime>16</DisplayTime>
      <Font FontFamily="Yu Gothic UI" Size="30" Stretch="Normal" Style="Normal" Weight="Normal" />
      <FontColor>#FFFFFF</FontColor>
      <FontOutlineColor>#DC143C</FontOutlineColor>
      <BarBlurRadius>14</BarBlurRadius>
      <BackgroundAlpha>0</BackgroundAlpha>
      <BackgroundColor>#FFFFFF</BackgroundColor>
      <AddMessageEnabled>false</AddMessageEnabled>
      <ProgressBarEnabled>true</ProgressBarEnabled>
      <JobFilter />
      <PartyJobFilter />
      <PartyCompositionFilter />
      <ZoneFilter>733</ZoneFilter>
      <TimersMustRunningForStart />
      <TimersMustStoppingForStart />
      <ExpressionFilter>
        <expression />
        <expression />
        <expression />
        <expression />
      </ExpressionFilter>
      <IsSequentialTTS>false</IsSequentialTTS>
      <MatchTextToSpeak />
      <DelayTextToSpeak />
      <MatchAdvancedConfig>
        <IsEnabled>false</IsEnabled>
        <ToMainDevice>true</ToMainDevice>
        <ToSubDevice>false</ToSubDevice>
        <ToDicordTextChat>false</ToDicordTextChat>
        <Palette>Default</Palette>
      </MatchAdvancedConfig>
      <DelayAdvancedConfig>
        <IsEnabled>false</IsEnabled>
        <ToMainDevice>true</ToMainDevice>
        <ToSubDevice>false</ToSubDevice>
        <ToDicordTextChat>false</ToDicordTextChat>
        <Palette>Default</Palette>
      </DelayAdvancedConfig>
      <DelaySound />
      <MatchSound />
    </OnePointTelop>
    <OnePointTelop>
      <SortPriority>0</SortPriority>
      <IsChecked>false</IsChecked>
      <IsExpanded>false</IsExpanded>
      <Enabled>true</Enabled>
      <ID>6</ID>
      <Guid>96d34ec1-512c-43bd-a583-f9dbddaaad22</Guid>
      <Left>1080</Left>
      <Top>680</Top>
      <Title>02_チェインライトニング</Title>
      <Message>雷{COUNT0}</Message>
      <RegexEnabled>false</RegexEnabled>
      <Keyword>00:302b:サンダーウィングの「チェインライトニング」</Keyword>
      <Delay>0</Delay>
      <DisplayTime>5</DisplayTime>
      <Font FontFamily="Yu Gothic UI" Size="30" Stretch="Normal" Style="Normal" Weight="Normal" />
      <FontColor>#FFFFFF</FontColor>
      <FontOutlineColor>#DC143C</FontOutlineColor>
      <BarBlurRadius>14</BarBlurRadius>
      <BackgroundAlpha>0</BackgroundAlpha>
      <BackgroundColor>#FFFFFF</BackgroundColor>
      <AddMessageEnabled>false</AddMessageEnabled>
      <ProgressBarEnabled>true</ProgressBarEnabled>
      <JobFilter />
      <PartyJobFilter />
      <PartyCompositionFilter />
      <ZoneFilter>733</ZoneFilter>
      <TimersMustRunningForStart />
      <TimersMustStoppingForStart />
      <ExpressionFilter>
        <expression />
        <expression />
        <expression />
        <expression />
      </ExpressionFilter>
      <IsSequentialTTS>false</IsSequentialTTS>
      <MatchTextToSpeak />
      <DelayTextToSpeak />
      <MatchAdvancedConfig>
        <IsEnabled>false</IsEnabled>
        <ToMainDevice>true</ToMainDevice>
        <ToSubDevice>false</ToSubDevice>
        <ToDicordTextChat>false</ToDicordTextChat>
        <Palette>Default</Palette>
      </MatchAdvancedConfig>
      <DelayAdvancedConfig>
        <IsEnabled>false</IsEnabled>
        <ToMainDevice>true</ToMainDevice>
        <ToSubDevice>false</ToSubDevice>
        <ToDicordTextChat>false</ToDicordTextChat>
        <Palette>Default</Palette>
      </DelayAdvancedConfig>
      <DelaySound />
      <MatchSound />
    </OnePointTelop>
    <OnePointTelop>
      <SortPriority>0</SortPriority>
      <IsChecked>false</IsChecked>
      <IsExpanded>false</IsExpanded>
      <Enabled>true</Enabled>
      <ID>10</ID>
      <Guid>475a6416-4e69-4776-aa08-5a79889dde81</Guid>
      <Left>1230</Left>
      <Top>630</Top>
      <Title>ファイアボール</Title>
      <Message>自分にファイアボール</Message>
      <RegexEnabled>false</RegexEnabled>
      <Keyword>^23:&lt;id8&gt;:ファイアホーン:&lt;id8&gt;:&lt;mex&gt;:&lt;id4&gt;:0000:0005:&lt;id8&gt;:000F:</Keyword>
      <Delay>0</Delay>
      <DisplayTime>5</DisplayTime>
      <Font FontFamily="Yu Gothic UI" Size="30" Stretch="Normal" Style="Normal" Weight="Normal" />
      <FontColor>#FFFFFF</FontColor>
      <FontOutlineColor>#DC143C</FontOutlineColor>
      <BarBlurRadius>14</BarBlurRadius>
      <BackgroundAlpha>0</BackgroundAlpha>
      <BackgroundColor>#FFFFFF</BackgroundColor>
      <AddMessageEnabled>false</AddMessageEnabled>
      <ProgressBarEnabled>true</ProgressBarEnabled>
      <JobFilter />
      <PartyJobFilter />
      <PartyCompositionFilter />
      <ZoneFilter>733</ZoneFilter>
      <TimersMustRunningForStart />
      <TimersMustStoppingForStart />
      <ExpressionFilter>
        <expression />
        <expression />
        <expression />
        <expression />
      </ExpressionFilter>
      <IsSequentialTTS>false</IsSequentialTTS>
      <MatchTextToSpeak />
      <DelayTextToSpeak />
      <MatchAdvancedConfig>
        <IsEnabled>false</IsEnabled>
        <ToMainDevice>true</ToMainDevice>
        <ToSubDevice>false</ToSubDevice>
        <ToDicordTextChat>false</ToDicordTextChat>
        <Palette>Default</Palette>
      </MatchAdvancedConfig>
      <DelayAdvancedConfig>
        <IsEnabled>false</IsEnabled>
        <ToMainDevice>true</ToMainDevice>
        <ToSubDevice>false</ToSubDevice>
        <ToDicordTextChat>false</ToDicordTextChat>
        <Palette>Default</Palette>
      </DelayAdvancedConfig>
      <DelaySound />
      <MatchSound />
    </OnePointTelop>
  </Tickers>
</Exports>